Workbook

Sheet Zielliste
A1: Nr | B1: Prio | C1: Unternehmen | D1: Ort | E1: Kanton | F1: Segment | G1: Was sie herstellen / was am Standort läuft | H1: Umsatz (Mio, Orig.) | I1: Whg. | J1: Umsatz CHF Mio | K1: Grössenklasse | L1: GJ | M1: Mitarbeiter | N1: Eigentümer / Kotierung | O1: Datenqualität | P1: Kategorie | Q1: Mandat / Hinweis | R1: Fit-Score (1-5) | S1: Kontakt im Netzwerk | T1: Status | U1: Notizen | V1: Quelle | W1: jobs.ch-Suchbegriff | X1: jobs.ch-Suche | Y1: Karriereseite (geprüft)
A2: 1 | B2: 1 | C2: ABB | D2: Zürich | E2: ZH | F2: Elektrotechnik/Automation | G2: Elektrifizierung, Antriebe, Robotik, Prozessautomation | H2: 33220 | I2: USD | J2: =IF(H2="","",H2*IF(I2="CHF",1,IF(I2="EUR",'Legende & Kriterien'!$C$13,'Legende & Kriterien'!$C$14))) | K2: =IF(P2="Rohstoffhandel","— Handel —",IF(J2="","k.A.",IF(J2>=5000,"A: >5 Mrd.",IF(J2>=3000,"B: 3-5 Mrd.",IF(J2>=1000,"C: 1-3 Mrd.","D: 0.1-1 Mrd."))))) | L2: 2025 | M2: 111900 | N2: SIX + Nasdaq Stockholm: ABBN | O2: publiziert | P2: Grosskonzern | V2: https://www.abb.com/global/en/company/annual-reporting-suite/key-figures | W2: ABB | X2: Stellen suchen | Y2: https://www.jobs.ch/en/companies/55089-abb-schweiz-ag/
A3: 2 | B3: 1 | C3: Amcor | D3: Zürich | E3: ZH | F3: Verpackung | G3: Flexible und starre Verpackungen, Verschlüsse, Spendersysteme | H3: 23506 | I3: USD | J3: =IF(H3="","",H3*IF(I3="CHF",1,IF(I3="EUR",'Legende & Kriterien'!$C$13,'Legende & Kriterien'!$C$14))) | K3: =IF(P3="Rohstoffhandel","— Handel —",IF(J3="","k.A.",IF(J3>=5000,"A: >5 Mrd.",IF(J3>=3000,"B: 3-5 Mrd.",IF(J3>=1000,"C: 1-3 Mrd.","D: 0.1-1 Mrd."))))) | L3: 2025/26 | M3: 75000 | N3: NYSE + ASX: AMCR | O3: publiziert | P3: Grosskonzern | Q3: Jersey-Recht; ab 2027 Verlagerung von Konzernfunktionen nach Miami | V3: https://www.amcor.com/investors | W3: Amcor | X3: Stellen suchen | Y3: https://amcor.wd5.myworkdayjobs.com/Amcor_External_Career_Site — nicht abrufbar ohne Rendern, Workday
A4: 3 | B4: 1 | C4: Hitachi Energy | D4: Zürich | E4: ZH | F4: Energie-/Netztechnik | G4: Transformatoren, HGÜ, Hochspannungsprodukte, Netzautomation | H4: 20000 | I4: USD | J4: =IF(H4="","",H4*IF(I4="CHF",1,IF(I4="EUR",'Legende & Kriterien'!$C$13,'Legende & Kriterien'!$C$14))) | K4: =IF(P4="Rohstoffhandel","— Handel —",IF(J4="","k.A.",IF(J4>=5000,"A: >5 Mrd.",IF(J4>=3000,"B: 3-5 Mrd.",IF(J4>=1000,"C: 1-3 Mrd.","D: 0.1-1 Mrd."))))) | L4: 2026 | M4: 56000 | N4: Hitachi Ltd. (JP), nicht kotiert | O4: geschätzt | P4: Grosskonzern | Q4: Kein separat testierter Abschluss; Zahl ist Unternehmensangabe | V4: https://www.hitachienergy.com/company/company-profile | W4: Hitachi Energy | X4: Stellen suchen | Y4: https://careers.hitachi.com/search/hitachi-energy/jobs/in/country/switzerland
A5: 4 | B5: 1 | C5: Holcim | D5: Zug | E5: ZG | F5: Baustoffe | G5: Zement, Beton, Zuschlagstoffe, Dach- und Dämmsysteme | H5: 15724 | I5: CHF | J5: =IF(H5="","",H5*IF(I5="CHF",1,IF(I5="EUR",'Legende & Kriterien'!$C$13,'Legende & Kriterien'!$C$14))) | K5: =IF(P5="Rohstoffhandel","— Handel —",IF(J5="","k.A.",IF(J5>=5000,"A: >5 Mrd.",IF(J5>=3000,"B: 3-5 Mrd.",IF(J5>=1000,"C: 1-3 Mrd.","D: 0.1-1 Mrd."))))) | L5: 2025 | M5: 45000 | N5: SIX: HOLN | O5: publiziert | P5: Grosskonzern | Q5: Nach Abspaltung von Amrize | V5: https://www.holcim.com/media/media-releases/full-year-2025-results | W5: Holcim | X5: Stellen suchen | Y5: https://careers.holcimgroup.com/search/
A6: 5 | B6: 1 | C6: Liebherr-International | D6: Bulle | E6: FR | F6: Maschinen-/Anlagenbau | G6: Baumaschinen, Krane, Bergbaugeräte, Kühlgeräte, Luftfahrtkomponenten | H6: 14772 | I6: EUR | J6: =IF(H6="","",H6*IF(I6="CHF",1,IF(I6="EUR",'Legende & Kriterien'!$C$13,'Legende & Kriterien'!$C$14))) | K6: =IF(P6="Rohstoffhandel","— Handel —",IF(J6="","k.A.",IF(J6>=5000,"A: >5 Mrd.",IF(J6>=3000,"B: 3-5 Mrd.",IF(J6>=1000,"C: 1-3 Mrd.","D: 0.1-1 Mrd."))))) | L6: 2025 | M6: 55963 | N6: Familie Liebherr, nicht kotiert | O6: publiziert | P6: Grosskonzern | Q6: GB 2025 nennt Nussbaumen AG als Konzernadresse — HQ-Angabe uneinheitlich | V6: https://www.liebherr.com/en-us/n/liebherr-sees-stable-growth-in-the-2025-business-year-244544-3782185 | W6: Liebherr | X6: Stellen suchen | Y6: https://www.liebherr.com/de/deu/karriere/offene-stellen/offene-stellen.html
A7: 6 | B7: 1 | C7: Sika | D7: Baar | E7: ZG | F7: Bauchemie/Spezialchemie | G7: Bauchemie, Klebstoffe, Dichtstoffe, Mörtel, Abdichtungsbahnen | H7: 11201 | I7: CHF | J7: =IF(H7="","",H7*IF(I7="CHF",1,IF(I7="EUR",'Legende & Kriterien'!$C$13,'Legende & Kriterien'!$C$14))) | K7: =IF(P7="Rohstoffhandel","— Handel —",IF(J7="","k.A.",IF(J7>=5000,"A: >5 Mrd.",IF(J7>=3000,"B: 3-5 Mrd.",IF(J7>=1000,"C: 1-3 Mrd.","D: 0.1-1 Mrd."))))) | L7: 2025 | M7: 33707 | N7: SIX: SIKA | O7: publiziert | P7: Grosskonzern | V7: https://www.sika.com/en/media/media-releases/2026/sika-reports-full-year-2025-results.html | W7: Sika | X7: Stellen suchen | Y7: https://www.sika.com/en/career/jobs.html — nicht abrufbar ohne Rendern, JS-Widget
A8: 7 | B8: 1 | C8: Schindler | D8: Ebikon | E8: LU | F8: Gebäudetechnik/Maschinenbau | G8: Aufzüge, Fahrtreppen, Fahrsteige, Modernisierung, Wartung | H8: 10947 | I8: CHF | J8: =IF(H8="","",H8*IF(I8="CHF",1,IF(I8="EUR",'Legende & Kriterien'!$C$13,'Legende & Kriterien'!$C$14))) | K8: =IF(P8="Rohstoffhandel","— Handel —",IF(J8="","k.A.",IF(J8>=5000,"A: >5 Mrd.",IF(J8>=3000,"B: 3-5 Mrd.",IF(J8>=1000,"C: 1-3 Mrd.","D: 0.1-1 Mrd."))))) | L8: 2025 | M8: 67000 | N8: SIX: SCHN/SCHP, Familien Schindler/Bonnard | O8: publiziert | P8: Grosskonzern | V8: https://group.schindler.com/en/media/press-releases/annual-results-2025.html | W8: Schindler | X8: Stellen suchen | Y8: https://job.schindler.com/search/
A9: 8 | B9: 1 | C9: STMicroelectronics | D9: Plan-les-Ouates (Genf) | E9: GE | F9: Halbleiter | G9: Mikrocontroller, Leistungshalbleiter, Sensoren, Analog-Chips | H9: 11800 | I9: USD | J9: =IF(H9="","",H9*IF(I9="CHF",1,IF(I9="EUR",'Legende & Kriterien'!$C$13,'Legende & Kriterien'!$C$14))) | K9: =IF(P9="Rohstoffhandel","— Handel —",IF(J9="","k.A.",IF(J9>=5000,"A: >5 Mrd.",IF(J9>=3000,"B: 3-5 Mrd.",IF(J9>=1000,"C: 1-3 Mrd.","D: 0.1-1 Mrd."))))) | L9: 2025 | M9: 48000 | N9: NYSE / Euronext Paris / Borsa Italiana | O9: publiziert | P9: Grenzfall | Q9: Operativer HQ Genf, statutarischer Sitz Amsterdam (NL) | V9: https://www.globenewswire.com/news-release/2026/01/29/3228178/0/en/STMicroelectronics-Reports-Q4-and-FY-2025-Financial-Results.html | W9: STMicroelectronics | X9: Stellen suchen | Y9: https://stmicroelectronics.eightfold.ai/careers — nicht abrufbar ohne Rendern, Eightfold-SPA
A10: 9 | B10: 1 | C10: Alcon | D10: Genf | E10: GE | F10: Medtech/Ophthalmologie | G10: Intraokularlinsen, Kontaktlinsen, Augenchirurgie-Systeme | H10: 10319 | I10: USD | J10: =IF(H10="","",H10*IF(I10="CHF",1,IF(I10="EUR",'Legende & Kriterien'!$C$13,'Legende & Kriterien'!$C$14))) | K10: =IF(P10="Rohstoffhandel","— Handel —",IF(J10="","k.A.",IF(J10>=5000,"A: >5 Mrd.",IF(J10>=3000,"B: 3-5 Mrd.",IF(J10>=1000,"C: 1-3 Mrd.","D: 0.1-1 Mrd."))))) | L10: 2025 | M10: 25000 | N10: SIX + NYSE: ALC | O10: publiziert | P10: Grosskonzern | Q10: Statutarischer Sitz im Kanton Freiburg | V10: https://www.alcon.com/investor-relations | W10: Alcon | X10: Stellen suchen | Y10: https://alcon.wd5.myworkdayjobs.com/careers_alcon — nicht abrufbar ohne Rendern, Workday
A11: 10 | B11: 1 | C11: SGS | D11: Baar | E11: ZG | F11: Prüf-/Zertifizierungsdienste | G11: Kein Hersteller: Prüfung, Inspektion, Verifizierung, Zertifizierung | H11: 6945 | I11: CHF | J11: =IF(H11="","",H11*IF(I11="CHF",1,IF(I11="EUR",'Legende & Kriterien'!$C$13,'Legende & Kriterien'!$C$14))) | K11: =IF(P11="Rohstoffhandel","— Handel —",IF(J11="","k.A.",IF(J11>=5000,"A: >5 Mrd.",IF(J11>=3000,"B: 3-5 Mrd.",IF(J11>=1000,"C: 1-3 Mrd.","D: 0.1-1 Mrd."))))) | L11: 2025 | M11: 100000 | N11: SIX: SGSN | O11: publiziert | P11: Grenzfall | Q11: Dienstleister, kein Engineered Product — nur zur Vollständigkeit | V11: https://www.sgs.com/en/news/2026/02/2025-full-year-results | W11: SGS | X11: Stellen suchen | Y11: https://careers.smartrecruiters.com/SGS
A12: 11 | B12: 1 | C12: Hilti | D12: Schaan | E12: FL | F12: Bau-/Werkzeugtechnik | G12: Bohr-, Befestigungs- und Messtechnik für die Bauindustrie | H12: 6297 | I12: CHF | J12: =IF(H12="","",H12*IF(I12="CHF",1,IF(I12="EUR",'Legende & Kriterien'!$C$13,'Legende & Kriterien'!$C$14))) | K12: =IF(P12="Rohstoffhandel","— Handel —",IF(J12="","k.A.",IF(J12>=5000,"A: >5 Mrd.",IF(J12>=3000,"B: 3-5 Mrd.",IF(J12>=1000,"C: 1-3 Mrd.","D: 0.1-1 Mrd."))))) | L12: 2025 | M12: 34420 | N12: Martin Hilti Familientreuhänderschaft | O12: publiziert | P12: Liechtenstein | V12: https://www.hilti.group/content/hilti/CP/XX/en/company/media-relations/media-releases/2025-business-result.html | W12: Hilti | X12: Stellen suchen | Y12: https://careers.hilti.group/en-us/jobs/
A13: 12 | B13: 1 | C13: Swatch Group | D13: Biel/Bienne | E13: BE | F13: Uhren/Mikrotechnik | G13: Uhren, Uhrwerke, Schmuck, elektronische Komponenten, Mikromechanik | H13: 6280 | I13: CHF | J13: =IF(H13="","",H13*IF(I13="CHF",1,IF(I13="EUR",'Legende & Kriterien'!$C$13,'Legende & Kriterien'!$C$14))) | K13: =IF(P13="Rohstoffhandel","— Handel —",IF(J13="","k.A.",IF(J13>=5000,"A: >5 Mrd.",IF(J13>=3000,"B: 3-5 Mrd.",IF(J13>=1000,"C: 1-3 Mrd.","D: 0.1-1 Mrd."))))) | L13: 2025 | M13: 31800 | N13: SIX: UHR/UHRN, Familie Hayek | O13: publiziert | P13: Grosskonzern | V13: https://www.swatchgroup.com/en/services/archive/2026/key-figures-2025 | W13: Swatch | X13: Stellen suchen | Y13: https://www.swatchgroup.com/en/job-finder
A14: 13 | B14: 1 | C14: Garmin | D14: Schaffhausen | E14: SH | F14: Elektronik/Navigation | G14: GPS-Navigation, Smartwatches, Avionik, Marine- und Outdoor-Geräte | H14: 7250 | I14: USD | J14: =IF(H14="","",H14*IF(I14="CHF",1,IF(I14="EUR",'Legende & Kriterien'!$C$13,'Legende & Kriterien'!$C$14))) | K14: =IF(P14="Rohstoffhandel","— Handel —",IF(J14="","k.A.",IF(J14>=5000,"A: >5 Mrd.",IF(J14>=3000,"B: 3-5 Mrd.",IF(J14>=1000,"C: 1-3 Mrd.","D: 0.1-1 Mrd."))))) | L14: 2025 | M14: 23000 | N14: NYSE: GRMN | O14: publiziert | P14: Grenzfall | Q14: Statutarischer Sitz Schaffhausen, operativer HQ Olathe (Kansas, USA) | V14: https://www8.garmin.com/aboutGarmin/invRelations/reports/2025_Form_10-K.pdf | W14: Garmin | X14: Stellen suchen | Y14: https://careers.garmin.com/jobs — nicht abrufbar ohne Rendern, JS
A15: 14 | B15: 1 | C15: Georg Fischer (GF) | D15: Schaffhausen | E15: SH | F15: Maschinenbau/Fluidtechnik | G15: Rohrleitungssysteme, Armaturen, Wasserbehandlung, Präzisionsfertigung | H15: 4110 | I15: CHF | J15: =IF(H15="","",H15*IF(I15="CHF",1,IF(I15="EUR",'Legende & Kriterien'!$C$13,'Legende & Kriterien'!$C$14))) | K15: =IF(P15="Rohstoffhandel","— Handel —",IF(J15="","k.A.",IF(J15>=5000,"A: >5 Mrd.",IF(J15>=3000,"B: 3-5 Mrd.",IF(J15>=1000,"C: 1-3 Mrd.","D: 0.1-1 Mrd."))))) | L15: 2025 | M15: 16332 | N15: SIX: GF | O15: publiziert | P15: Grosskonzern | Q15: Machining Solutions 2025 an United Grinding verkauft | V15: https://www.georgfischer.com/content/dam/gfcorp/documents/newsroom/media-releases/annual-report-2025/20260225-ad-hoc-announcement-annual-report-2025-en.pdf | W15: Georg Fischer | X15: Stellen suchen | Y15: https://www.georgfischer.com/content/gfcorp/com/en/career/vacancies.html — nicht abrufbar ohne Rendern, Workday
A16: 15 | B16: 1 | C16: Clariant | D16: Muttenz | E16: BL | F16: Spezialchemie | G16: Spezialchemikalien, Katalysatoren, Adsorbentien, Additive | H16: 3915 | I16: CHF | J16: =IF(H16="","",H16*IF(I16="CHF",1,IF(I16="EUR",'Legende & Kriterien'!$C$13,'Legende & Kriterien'!$C$14))) | K16: =IF(P16="Rohstoffhandel","— Handel —",IF(J16="","k.A.",IF(J16>=5000,"A: >5 Mrd.",IF(J16>=3000,"B: 3-5 Mrd.",IF(J16>=1000,"C: 1-3 Mrd.","D: 0.1-1 Mrd."))))) | L16: 2025 | M16: 10281 | N16: SIX: CLN | O16: publiziert | P16: Grosskonzern | V16: https://www.clariant.com/en/Corporate/News/2026/02/Clariant-delivers-third-year-of-strong-EBITDA-margin-improvement | W16: Clariant | X16: Stellen suchen | Y16: https://careers.clariant.com/search/
A17: 16 | B17: 1 | C17: Logitech | D17: Lausanne | E17: VD | F17: Elektronik/Peripherie | G17: Mäuse, Tastaturen, Headsets, Webcams, Videokonferenzgeräte | H17: 4841 | I17: USD | J17: =IF(H17="","",H17*IF(I17="CHF",1,IF(I17="EUR",'Legende & Kriterien'!$C$13,'Legende & Kriterien'!$C$14))) | K17: =IF(P17="Rohstoffhandel","— Handel —",IF(J17="","k.A.",IF(J17>=5000,"A: >5 Mrd.",IF(J17>=3000,"B: 3-5 Mrd.",IF(J17>=1000,"C: 1-3 Mrd.","D: 0.1-1 Mrd."))))) | L17: 2025/26 | M17: 7300 | N17: SIX + Nasdaq: LOGN/LOGI | O17: publiziert | P17: Grosskonzern | Q17: Doppelsitz Lausanne / San Jose | V17: https://www.businesswire.com/news/home/20260505206276/en/Logitech-Announces-Q4-and-Full-Fiscal-Year-2026-Results | W17: Logitech | X17: Stellen suchen | Y17: https://logitech.wd5.myworkdayjobs.com/en-US/Logitech — nicht abrufbar ohne Rendern, Workday (CH ggf. robots-gesperrt)
A18: 17 | B18: 1 | C18: Endress+Hauser | D18: Reinach | E18: BL | F18: Prozessmesstechnik | G18: Messgeräte für Füllstand, Druck, Durchfluss, Analyse | H18: 4010 | I18: EUR | J18: =IF(H18="","",H18*IF(I18="CHF",1,IF(I18="EUR",'Legende & Kriterien'!$C$13,'Legende & Kriterien'!$C$14))) | K18: =IF(P18="Rohstoffhandel","— Handel —",IF(J18="","k.A.",IF(J18>=5000,"A: >5 Mrd.",IF(J18>=3000,"B: 3-5 Mrd.",IF(J18>=1000,"C: 1-3 Mrd.","D: 0.1-1 Mrd."))))) | L18: 2025 | M18: 18306 | N18: Familie Endress (100%) | O18: publiziert | P18: Grosskonzern | V18: https://www.muehle-mischfutter.de/artikel/endress-hauser-2025-uber-vier-mrd--euro-umsatz | W18: Endress Hauser | X18: Stellen suchen | Y18: https://careers.endress.com/Switzerland/content/search/?locale=en_US — nicht abrufbar ohne Rendern, Cookie-Wall
A19: 18 | B19: 1 | C19: Stadler Rail | D19: Bussnang | E19: TG | F19: Schienenfahrzeugbau | G19: Triebzüge, Trams, Lokomotiven, Signaltechnik, Fahrzeugservice | H19: 3679 | I19: CHF | J19: =IF(H19="","",H19*IF(I19="CHF",1,IF(I19="EUR",'Legende & Kriterien'!$C$13,'Legende & Kriterien'!$C$14))) | K19: =IF(P19="Rohstoffhandel","— Handel —",IF(J19="","k.A.",IF(J19>=5000,"A: >5 Mrd.",IF(J19>=3000,"B: 3-5 Mrd.",IF(J19>=1000,"C: 1-3 Mrd.","D: 0.1-1 Mrd."))))) | L19: 2025 | M19: 17100 | N19: SIX: SRAIL, PCS Holding (P. Spuhler) | O19: publiziert | P19: Grosskonzern | Q19: Rund 6'000 Mitarbeitende in der Schweiz | V19: https://www.stadlerrail.com/en/investors/ | W19: Stadler Rail | X19: Stellen suchen | Y19: https://jobs.stadlerrail.ch/
A20: 19 | B20: 1 | C20: Sonova | D20: Stäfa | E20: ZH | F20: Medizintechnik | G20: Hörgeräte, Cochlea-Implantate, drahtlose Audiosysteme | H20: 3606 | I20: CHF | J20: =IF(H20="","",H20*IF(I20="CHF",1,IF(I20="EUR",'Legende & Kriterien'!$C$13,'Legende & Kriterien'!$C$14))) | K20: =IF(P20="Rohstoffhandel","— Handel —",IF(J20="","k.A.",IF(J20>=5000,"A: >5 Mrd.",IF(J20>=3000,"B: 3-5 Mrd.",IF(J20>=1000,"C: 1-3 Mrd.","D: 0.1-1 Mrd."))))) | L20: 2025/26 | M20: 18000 | N20: SIX: SOON | O20: publiziert | P20: Grosskonzern | V20: https://report.sonova.com/2026/en/startpage | W20: Sonova | X20: Stellen suchen | Y20: https://jobs.sonova.com/go/All-Jobs/4577301/
A21: 20 | B21: 1 | C21: Sulzer | D21: Winterthur | E21: ZH | F21: Maschinenbau/Anlagentechnik | G21: Pumpen, Rührwerke, Trennkolonnen, Strömungsmaschinen und Service | H21: 3555 | I21: CHF | J21: =IF(H21="","",H21*IF(I21="CHF",1,IF(I21="EUR",'Legende & Kriterien'!$C$13,'Legende & Kriterien'!$C$14))) | K21: =IF(P21="Rohstoffhandel","— Handel —",IF(J21="","k.A.",IF(J21>=5000,"A: >5 Mrd.",IF(J21>=3000,"B: 3-5 Mrd.",IF(J21>=1000,"C: 1-3 Mrd.","D: 0.1-1 Mrd."))))) | L21: 2025 | M21: 13526 | N21: SIX: SUN, Grossaktionärin Tiwel | O21: publiziert | P21: Grosskonzern | V21: https://www.sulzer.com/en/-/media/files/news/2026/20260226sulzer-exceeds-chf-550-million-ebitda.pdf | W21: Sulzer | X21: Stellen suchen | Y21: https://sulzer.wd502.myworkdayjobs.com/SulzerJobs — nicht abrufbar ohne Rendern, Workday
A22: 21 | B22: 1 | C22: Mettler-Toledo | D22: Greifensee | E22: ZH | F22: Mess-/Wäge-/Analysetechnik | G22: Präzisionswaagen, Laborinstrumente, Pipetten, Produktinspektionssysteme | H22: 4026 | I22: USD | J22: =IF(H22="","",H22*IF(I22="CHF",1,IF(I22="EUR",'Legende & Kriterien'!$C$13,'Legende & Kriterien'!$C$14))) | K22: =IF(P22="Rohstoffhandel","— Handel —",IF(J22="","k.A.",IF(J22>=5000,"A: >5 Mrd.",IF(J22>=3000,"B: 3-5 Mrd.",IF(J22>=1000,"C: 1-3 Mrd.","D: 0.1-1 Mrd."))))) | L22: 2025 | M22: 18100 | N22: NYSE: MTD | O22: publiziert | P22: Grenzfall | Q22: Delaware-Gesellschaft mit Doppelsitz Greifensee / Columbus (Ohio) | V22: https://investor.mt.com/news/news-details/2026/Mettler-Toledo-International-Inc--Reports-Fourth-Quarter-2025-Results/default.aspx | W22: Mettler-Toledo | X22: Stellen suchen | Y22: https://jobs.mt.com/en/search-jobs
A23: 22 | B23: 1 | C23: Geberit | D23: Rapperswil-Jona | E23: SG | F23: Sanitär-/Gebäudetechnik | G23: Sanitärtechnik, Rohrleitungssysteme, Spülkästen, Badkeramik | H23: 3163 | I23: CHF | J23: =IF(H23="","",H23*IF(I23="CHF",1,IF(I23="EUR",'Legende & Kriterien'!$C$13,'Legende & Kriterien'!$C$14))) | K23: =IF(P23="Rohstoffhandel","— Handel —",IF(J23="","k.A.",IF(J23>=5000,"A: >5 Mrd.",IF(J23>=3000,"B: 3-5 Mrd.",IF(J23>=1000,"C: 1-3 Mrd.","D: 0.1-1 Mrd."))))) | L23: 2025 | M23: 11278 | N23: SIX: GEBN | O23: publiziert | P23: Grosskonzern | V23: https://www.geberit.com/assets/downloads/media-releases/2026/media-release-annual-results-2025.pdf | W23: Geberit | X23: Stellen suchen | Y23: https://www.geberit.ch/karriere/ — nicht abrufbar ohne Rendern, Navigation unklar
A24: 23 | B24: 2 | C24: ams-OSRAM | D24: Premstätten (AT) | E24: – | F24: Halbleiter/Photonik | G24: Optische Sensoren, LEDs, Fahrzeuglampen, Photonik-Bauelemente | H24: 3300 | I24: EUR | J24: =IF(H24="","",H24*IF(I24="CHF",1,IF(I24="EUR",'Legende & Kriterien'!$C$13,'Legende & Kriterien'!$C$14))) | K24: =IF(P24="Rohstoffhandel","— Handel —",IF(J24="","k.A.",IF(J24>=5000,"A: >5 Mrd.",IF(J24>=3000,"B: 3-5 Mrd.",IF(J24>=1000,"C: 1-3 Mrd.","D: 0.1-1 Mrd."))))) | L24: 2025 | M24: 18500 | N24: SIX: AMS | O24: publiziert | P24: Grenzfall | Q24: Sitz Österreich — nur an der SIX kotiert | V24: https://ams-osram.com/press/corporate-info | W24: ams-OSRAM | X24: Stellen suchen
A25: 24 | B25: 2 | C25: SFS Group | D25: Heerbrugg (Widnau) | E25: SG | F25: Präzisionsteile/Verbindungstechnik | G25: Präzisionsformteile, Befestigungssysteme, medizintechnische Komponenten | H25: 3057 | I25: CHF | J25: =IF(H25="","",H25*IF(I25="CHF",1,IF(I25="EUR",'Legende & Kriterien'!$C$13,'Legende & Kriterien'!$C$14))) | K25: =IF(P25="Rohstoffhandel","— Handel —",IF(J25="","k.A.",IF(J25>=5000,"A: >5 Mrd.",IF(J25>=3000,"B: 3-5 Mrd.",IF(J25>=1000,"C: 1-3 Mrd.","D: 0.1-1 Mrd."))))) | L25: 2025 | M25: 13600 | N25: SIX: SFSN, Familienaktionariat | O25: publiziert | P25: Grosskonzern | V25: https://www.sfs.com/ch/en/sfs-group/sfs-at-a-glance/ | W25: SFS | X25: Stellen suchen
A26: 25 | B26: 2 | C26: SIG Group | D26: Neuhausen a. Rhf. | E26: SH | F26: Verpackungssysteme | G26: Aseptische Kartonverpackungen, Beutel, Abfüllmaschinen | H26: 3249 | I26: EUR | J26: =IF(H26="","",H26*IF(I26="CHF",1,IF(I26="EUR",'Legende & Kriterien'!$C$13,'Legende & Kriterien'!$C$14))) | K26: =IF(P26="Rohstoffhandel","— Handel —",IF(J26="","k.A.",IF(J26>=5000,"A: >5 Mrd.",IF(J26>=3000,"B: 3-5 Mrd.",IF(J26>=1000,"C: 1-3 Mrd.","D: 0.1-1 Mrd."))))) | L26: 2025 | M26: 9700 | N26: SIX: SIGN | O26: publiziert | P26: Grosskonzern | V26: https://www.sig.biz/investors | W26: SIG | X26: Stellen suchen
A27: 26 | B27: 1 | C27: Bucher Industries | D27: Niederweningen | E27: ZH | F27: Maschinenbau | G27: Landmaschinen, Kommunalfahrzeuge, Hydraulik, Glasanlagen | H27: 2914 | I27: CHF | J27: =IF(H27="","",H27*IF(I27="CHF",1,IF(I27="EUR",'Legende & Kriterien'!$C$13,'Legende & Kriterien'!$C$14))) | K27: =IF(P27="Rohstoffhandel","— Handel —",IF(J27="","k.A.",IF(J27>=5000,"A: >5 Mrd.",IF(J27>=3000,"B: 3-5 Mrd.",IF(J27>=1000,"C: 1-3 Mrd.","D: 0.1-1 Mrd."))))) | L27: 2025 | M27: 12700 | N27: SIX: BUCN | O27: publiziert | P27: im Band | V27: https://stockanalysis.com/quote/swx/BUCN/financials/ | W27: Bucher Municipal | X27: Stellen suchen | Y27: https://www.bucherindustries.com/en/career/vacancies — nicht abrufbar ohne Rendern, keine Konzernliste
A28: 27 | B28: 2 | C28: dormakaba | D28: Rümlang | E28: ZH | F28: Sicherheitstechnik | G28: Türtechnik, Schliesssysteme, Zutrittskontrolle | H28: 2870 | I28: CHF | J28: =IF(H28="","",H28*IF(I28="CHF",1,IF(I28="EUR",'Legende & Kriterien'!$C$13,'Legende & Kriterien'!$C$14))) | K28: =IF(P28="Rohstoffhandel","— Handel —",IF(J28="","k.A.",IF(J28>=5000,"A: >5 Mrd.",IF(J28>=3000,"B: 3-5 Mrd.",IF(J28>=1000,"C: 1-3 Mrd.","D: 0.1-1 Mrd."))))) | L28: 2024/25 | M28: 15400 | N28: SIX: DOKA | O28: publiziert | P28: im Band | V28: https://stockanalysis.com/quote/swx/DOKA/financials/ | W28: dormakaba | X28: Stellen suchen
A29: 28 | B29: 1 | C29: Bühler Group | D29: Uzwil | E29: SG | F29: Verfahrenstechnik | G29: Anlagen für Getreide-, Lebensmittel- und Materialverarbeitung, Druckguss | H29: 2753 | I29: CHF | J29: =IF(H29="","",H29*IF(I29="CHF",1,IF(I29="EUR",'Legende & Kriterien'!$C$13,'Legende & Kriterien'!$C$14))) | K29: =IF(P29="Rohstoffhandel","— Handel —",IF(J29="","k.A.",IF(J29>=5000,"A: >5 Mrd.",IF(J29>=3000,"B: 3-5 Mrd.",IF(J29>=1000,"C: 1-3 Mrd.","D: 0.1-1 Mrd."))))) | L29: 2025 | M29: 12300 | N29: Familie Bühler (100%) | O29: publiziert | P29: im Band | V29: https://www.moneycab.com/schweiz/buehler-buesst-2025-an-umsatz-ein/ | W29: Bühler | X29: Stellen suchen | Y29: https://www.buhlergroup.com/global/en/careers/jobs.html — nicht abrufbar ohne Rendern, JS
A30: 29 | B30: 3 | C30: Straumann | D30: Basel | E30: BS | F30: Medtech/Dental | G30: Dentalimplantate, Prothetik, digitale Kieferorthopädie | H30: 2605 | I30: CHF | J30: =IF(H30="","",H30*IF(I30="CHF",1,IF(I30="EUR",'Legende & Kriterien'!$C$13,'Legende & Kriterien'!$C$14))) | K30: =IF(P30="Rohstoffhandel","— Handel —",IF(J30="","k.A.",IF(J30>=5000,"A: >5 Mrd.",IF(J30>=3000,"B: 3-5 Mrd.",IF(J30>=1000,"C: 1-3 Mrd.","D: 0.1-1 Mrd."))))) | L30: 2025 | M30: 11800 | N30: SIX: STMN | O30: publiziert | P30: im Band | V30: https://stockanalysis.com/quote/swx/STMN/financials/ | W30: Straumann | X30: Stellen suchen
A31: 30 | B31: 3 | C31: Franke Group (Artemis) | D31: Aarburg | E31: AG | F31: Gebäudetechnik/Foodservice | G31: Küchensysteme, Grossküchentechnik, professionelle Kaffeemaschinen | H31: 2420 | I31: CHF | J31: =IF(H31="","",H31*IF(I31="CHF",1,IF(I31="EUR",'Legende & Kriterien'!$C$13,'Legende & Kriterien'!$C$14))) | K31: =IF(P31="Rohstoffhandel","— Handel —",IF(J31="","k.A.",IF(J31>=5000,"A: >5 Mrd.",IF(J31>=3000,"B: 3-5 Mrd.",IF(J31>=1000,"C: 1-3 Mrd.","D: 0.1-1 Mrd."))))) | L31: 2023 | M31: 8000 | N31: Familie Pieper (Artemis) | O31: veraltet | P31: im Band | Q31: Artemis-Gruppe gesamt CHF 2.88 Mrd. (2025) | V31: https://www.franke.com/de/de/gruppe/medien/2024/artemis-group-results-2024.html | W31: Franke | X31: Stellen suchen
A32: 31 | B32: 3 | C32: Swiss Steel | D32: Emmenbrücke | E32: LU | F32: Stahl/Materialien | G32: Spezialstahl-Langprodukte, Werkzeugstahl, Blankstahl | H32: 2511 | I32: EUR | J32: =IF(H32="","",H32*IF(I32="CHF",1,IF(I32="EUR",'Legende & Kriterien'!$C$13,'Legende & Kriterien'!$C$14))) | K32: =IF(P32="Rohstoffhandel","— Handel —",IF(J32="","k.A.",IF(J32>=5000,"A: >5 Mrd.",IF(J32>=3000,"B: 3-5 Mrd.",IF(J32>=1000,"C: 1-3 Mrd.","D: 0.1-1 Mrd."))))) | L32: 2024 | M32: 7450 | N32: SIX: STLN | O32: veraltet | P32: im Band | Q32: GJ 2025 nicht bestätigt | V32: https://stockanalysis.com/quote/swx/STLN/revenue/ | W32: Swiss Steel | X32: Stellen suchen
A33: 32 | B33: 3 | C33: Autoneum | D33: Winterthur | E33: ZH | F33: Automobilkomponenten | G33: Akustik- und Wärmedämmkomponenten für Fahrzeuge | H33: 2291 | I33: CHF | J33: =IF(H33="","",H33*IF(I33="CHF",1,IF(I33="EUR",'Legende & Kriterien'!$C$13,'Legende & Kriterien'!$C$14))) | K33: =IF(P33="Rohstoffhandel","— Handel —",IF(J33="","k.A.",IF(J33>=5000,"A: >5 Mrd.",IF(J33>=3000,"B: 3-5 Mrd.",IF(J33>=1000,"C: 1-3 Mrd.","D: 0.1-1 Mrd."))))) | L33: 2025 | M33: 16100 | N33: SIX: AUTN | O33: publiziert | P33: im Band | V33: https://stockanalysis.com/quote/swx/AUTN/financials/ | W33: Autoneum | X33: Stellen suchen
A34: 33 | B34: 3 | C34: EMS-CHEMIE | D34: Domat/Ems | E34: GR | F34: Materialien | G34: Hochleistungspolymere und Polyamide für Leichtbauteile | H34: 1969 | I34: CHF | J34: =IF(H34="","",H34*IF(I34="CHF",1,IF(I34="EUR",'Legende & Kriterien'!$C$13,'Legende & Kriterien'!$C$14))) | K34: =IF(P34="Rohstoffhandel","— Handel —",IF(J34="","k.A.",IF(J34>=5000,"A: >5 Mrd.",IF(J34>=3000,"B: 3-5 Mrd.",IF(J34>=1000,"C: 1-3 Mrd.","D: 0.1-1 Mrd."))))) | L34: 2025 | M34: 2660 | N34: SIX: EMSN | O34: publiziert | P34: im Band | V34: https://stockanalysis.com/quote/swx/EMSN/financials/ | W34: EMS-CHEMIE | X34: Stellen suchen
A35: 34 | B35: 3 | C35: Bobst Group | D35: Mex | E35: VD | F35: Verpackungsmaschinen | G35: Maschinen für Faltschachtel-, Wellpappe- und Etikettendruck | H35: 1800 | I35: CHF | J35: =IF(H35="","",H35*IF(I35="CHF",1,IF(I35="EUR",'Legende & Kriterien'!$C$13,'Legende & Kriterien'!$C$14))) | K35: =IF(P35="Rohstoffhandel","— Handel —",IF(J35="","k.A.",IF(J35>=5000,"A: >5 Mrd.",IF(J35>=3000,"B: 3-5 Mrd.",IF(J35>=1000,"C: 1-3 Mrd.","D: 0.1-1 Mrd."))))) | L35: 2024 | M35: 6000 | N35: Privat (Familie Bobst) | O35: geschätzt | P35: im Band | Q35: Dez. 2022 von der SIX dekotiert | V35: https://www.bobst.com/ | W35: Bobst Group | X35: Stellen suchen
A36: 35 | B36: 3 | C36: Pilatus Flugzeugwerke | D36: Stans | E36: NW | F36: Luftfahrt | G36: Trainings- und Geschäftsflugzeuge PC-12, PC-24, PC-21 | H36: 1672 | I36: CHF | J36: =IF(H36="","",H36*IF(I36="CHF",1,IF(I36="EUR",'Legende & Kriterien'!$C$13,'Legende & Kriterien'!$C$14))) | K36: =IF(P36="Rohstoffhandel","— Handel —",IF(J36="","k.A.",IF(J36>=5000,"A: >5 Mrd.",IF(J36>=3000,"B: 3-5 Mrd.",IF(J36>=1000,"C: 1-3 Mrd.","D: 0.1-1 Mrd."))))) | L36: 2025 | M36: 3678 | N36: Privat, CH-Aktionariat | O36: publiziert | P36: im Band | V36: https://www.pilatus-aircraft.com/assets/files/PDF/GB-2025/Pilatus-Geschaeftsbericht-2025.pdf | W36: Pilatus | X36: Stellen suchen
A37: 36 | B37: 1 | C37: Stäubli International | D37: Pfäffikon SZ | E37: SZ | F37: Automation/Robotik | G37: Industrieroboter, Schnellkupplungen, Steckverbinder, Webmaschinen | H37: 1600 | I37: CHF | J37: =IF(H37="","",H37*IF(I37="CHF",1,IF(I37="EUR",'Legende & Kriterien'!$C$13,'Legende & Kriterien'!$C$14))) | K37: =IF(P37="Rohstoffhandel","— Handel —",IF(J37="","k.A.",IF(J37>=5000,"A: >5 Mrd.",IF(J37>=3000,"B: 3-5 Mrd.",IF(J37>=1000,"C: 1-3 Mrd.","D: 0.1-1 Mrd."))))) | L37: 2024 | M37: 6000 | N37: Privat (Familienbesitz) | O37: geschätzt | P37: im Band | Q37: Publiziert keine Zahlen | V37: https://www.staubli.com/ch/de/home.html | W37: Stäubli | X37: Stellen suchen | Y37: https://careers.smartrecruiters.com/staubligroup
A38: 37 | B38: 3 | C38: OC Oerlikon | D38: Pfäffikon SZ | E38: SZ | F38: Materialien/Maschinenbau | G38: Oberflächenbeschichtungen, Polymerverarbeitungsanlagen | H38: 1568 | I38: CHF | J38: =IF(H38="","",H38*IF(I38="CHF",1,IF(I38="EUR",'Legende & Kriterien'!$C$13,'Legende & Kriterien'!$C$14))) | K38: =IF(P38="Rohstoffhandel","— Handel —",IF(J38="","k.A.",IF(J38>=5000,"A: >5 Mrd.",IF(J38>=3000,"B: 3-5 Mrd.",IF(J38>=1000,"C: 1-3 Mrd.","D: 0.1-1 Mrd."))))) | L38: 2025 | M38: 9290 | N38: SIX: OERL | O38: publiziert | P38: im Band | V38: https://stockanalysis.com/quote/swx/OERL/financials/ | W38: OC Oerlikon | X38: Stellen suchen
A39: 38 | B39: 3 | C39: Aebi Schmidt Group | D39: Frauenfeld | E39: TG | F39: Spezialfahrzeuge | G39: Winterdienst-, Kehr- und Spezialfahrzeuge, Nutzfahrzeugaufbauten | H39: 1900 | I39: USD | J39: =IF(H39="","",H39*IF(I39="CHF",1,IF(I39="EUR",'Legende & Kriterien'!$C$13,'Legende & Kriterien'!$C$14))) | K39: =IF(P39="Rohstoffhandel","— Handel —",IF(J39="","k.A.",IF(J39>=5000,"A: >5 Mrd.",IF(J39>=3000,"B: 3-5 Mrd.",IF(J39>=1000,"C: 1-3 Mrd.","D: 0.1-1 Mrd."))))) | L39: 2025 | M39: 6000 | N39: Nasdaq: AEBI (seit 07/2025) | O39: publiziert | P39: im Band | Q39: Fusion mit The Shyft Group 2025; CH-Sitz bestätigt | V39: https://www.aebi-schmidt.com/en/investors | W39: Aebi Schmidt | X39: Stellen suchen
A40: 39 | B40: 2 | C40: UNITED GRINDING Group | D40: Bern | E40: BE | F40: Werkzeugmaschinen | G40: Schleif-, Erodier- und Lasermaschinen (Studer, Walter, Blohm, GFMS) | H40: 1500 | I40: CHF | J40: =IF(H40="","",H40*IF(I40="CHF",1,IF(I40="EUR",'Legende & Kriterien'!$C$13,'Legende & Kriterien'!$C$14))) | K40: =IF(P40="Rohstoffhandel","— Handel —",IF(J40="","k.A.",IF(J40>=5000,"A: >5 Mrd.",IF(J40>=3000,"B: 3-5 Mrd.",IF(J40>=1000,"C: 1-3 Mrd.","D: 0.1-1 Mrd."))))) | L40: 2025 | M40: 4000 | N40: Patinex AG (M. Ebner) | O40: geschätzt | P40: im Band | Q40: GF Machining Solutions per 30.06.2025 übernommen | V40: https://www.grinding.ch/ | W40: United Grinding | X40: Stellen suchen
A41: 40 | B41: 2 | C41: Ammann Group | D41: Langenthal | E41: BE | F41: Baumaschinen | G41: Asphaltmischanlagen, Verdichtungs- und Strassenbaumaschinen | H41: 1200 | I41: EUR | J41: =IF(H41="","",H41*IF(I41="CHF",1,IF(I41="EUR",'Legende & Kriterien'!$C$13,'Legende & Kriterien'!$C$14))) | K41: =IF(P41="Rohstoffhandel","— Handel —",IF(J41="","k.A.",IF(J41>=5000,"A: >5 Mrd.",IF(J41>=3000,"B: 3-5 Mrd.",IF(J41>=1000,"C: 1-3 Mrd.","D: 0.1-1 Mrd."))))) | L41: 2024 | M41: 3600 | N41: Familie Ammann (100%) | O41: geschätzt | P41: im Band | V41: https://www.weltmarktfuehrerindex.de/profil/ammann | W41: Ammann | X41: Stellen suchen
A42: 41 | B42: 1 | C42: Belimo | D42: Hinwil | E42: ZH | F42: Bautechnik/HLK | G42: Stellantriebe, Ventile und Sensoren für HLK | H42: 1121 | I42: CHF | J42: =IF(H42="","",H42*IF(I42="CHF",1,IF(I42="EUR",'Legende & Kriterien'!$C$13,'Legende & Kriterien'!$C$14))) | K42: =IF(P42="Rohstoffhandel","— Handel —",IF(J42="","k.A.",IF(J42>=5000,"A: >5 Mrd.",IF(J42>=3000,"B: 3-5 Mrd.",IF(J42>=1000,"C: 1-3 Mrd.","D: 0.1-1 Mrd."))))) | L42: 2025 | M42: 2700 | N42: SIX: BEAN | O42: publiziert | P42: im Band | V42: https://www.belimo.com/ch/de_CH/about-belimo/investor-relations | W42: Belimo | X42: Stellen suchen | Y42: https://www.jobs.ch/en/companies/16954-belimo-automation-ag/
A43: 42 | B43: 1 | C43: Dätwyler | D43: Altdorf | E43: UR | F43: Komponenten/Materialien | G43: Elastomer-Dichtungen für Healthcare, Mobilität, Konsumgüter | H43: 1101 | I43: CHF | J43: =IF(H43="","",H43*IF(I43="CHF",1,IF(I43="EUR",'Legende & Kriterien'!$C$13,'Legende & Kriterien'!$C$14))) | K43: =IF(P43="Rohstoffhandel","— Handel —",IF(J43="","k.A.",IF(J43>=5000,"A: >5 Mrd.",IF(J43>=3000,"B: 3-5 Mrd.",IF(J43>=1000,"C: 1-3 Mrd.","D: 0.1-1 Mrd."))))) | L43: 2025 | M43: 7800 | N43: SIX: DAE | O43: publiziert | P43: im Band | V43: https://stockanalysis.com/quote/swx/DAE/financials/ | W43: Dätwyler | X43: Stellen suchen | Y43: https://careers.datwyler.com/search/
A44: 43 | B44: 2 | C44: Forbo | D44: Baar | E44: ZG | F44: Materialien/Bautechnik | G44: Bodenbeläge sowie Antriebs- und Transportbänder | H44: 1085 | I44: CHF | J44: =IF(H44="","",H44*IF(I44="CHF",1,IF(I44="EUR",'Legende & Kriterien'!$C$13,'Legende & Kriterien'!$C$14))) | K44: =IF(P44="Rohstoffhandel","— Handel —",IF(J44="","k.A.",IF(J44>=5000,"A: >5 Mrd.",IF(J44>=3000,"B: 3-5 Mrd.",IF(J44>=1000,"C: 1-3 Mrd.","D: 0.1-1 Mrd."))))) | L44: 2025 | M44: 5200 | N44: SIX: FORN | O44: publiziert | P44: im Band | V44: https://stockanalysis.com/quote/swx/FORN/financials/ | W44: Forbo | X44: Stellen suchen
A45: 44 | B45: 1 | C45: VAT Group | D45: Haag (Sennwald) | E45: SG | F45: Halbleiterausrüstung | G45: Hochvakuumventile für Halbleiter- und Displayfertigung | H45: 1074 | I45: CHF | J45: =IF(H45="","",H45*IF(I45="CHF",1,IF(I45="EUR",'Legende & Kriterien'!$C$13,'Legende & Kriterien'!$C$14))) | K45: =IF(P45="Rohstoffhandel","— Handel —",IF(J45="","k.A.",IF(J45>=5000,"A: >5 Mrd.",IF(J45>=3000,"B: 3-5 Mrd.",IF(J45>=1000,"C: 1-3 Mrd.","D: 0.1-1 Mrd."))))) | L45: 2025 | M45: 3960 | N45: SIX: VACN | O45: publiziert | P45: im Band | V45: https://stockanalysis.com/quote/swx/VACN/financials/ | W45: VAT Group | X45: Stellen suchen | Y45: https://careers.vatvalve.com/search/
A46: 45 | B46: 1 | C46: Bossard | D46: Zug | E46: ZG | F46: Komponenten/Verbindungstechnik | G46: Verbindungstechnik, C-Teile-Logistik, Engineering | H46: 1069 | I46: CHF | J46: =IF(H46="","",H46*IF(I46="CHF",1,IF(I46="EUR",'Legende & Kriterien'!$C$13,'Legende & Kriterien'!$C$14))) | K46: =IF(P46="Rohstoffhandel","— Handel —",IF(J46="","k.A.",IF(J46>=5000,"A: >5 Mrd.",IF(J46>=3000,"B: 3-5 Mrd.",IF(J46>=1000,"C: 1-3 Mrd.","D: 0.1-1 Mrd."))))) | L46: 2025 | M46: 3180 | N46: SIX: BOSN | O46: publiziert | P46: im Band | V46: https://stockanalysis.com/quote/swx/BOSN/financials/ | W46: Bossard | X46: Stellen suchen | Y46: https://www.jobs.ch/en/companies/3501-bossard-ag/
A47: 46 | B47: 1 | C47: Burckhardt Compression | D47: Winterthur | E47: ZH | F47: Maschinenbau | G47: Kolbenkompressoren für Öl, Gas und Wasserstoff | H47: 1057 | I47: CHF | J47: =IF(H47="","",H47*IF(I47="CHF",1,IF(I47="EUR",'Legende & Kriterien'!$C$13,'Legende & Kriterien'!$C$14))) | K47: =IF(P47="Rohstoffhandel","— Handel —",IF(J47="","k.A.",IF(J47>=5000,"A: >5 Mrd.",IF(J47>=3000,"B: 3-5 Mrd.",IF(J47>=1000,"C: 1-3 Mrd.","D: 0.1-1 Mrd."))))) | L47: 2025/26 | M47: 3300 | N47: SIX: BCHN | O47: publiziert | P47: im Band | V47: https://stockanalysis.com/quote/swx/BCHN/financials/ | W47: Burckhardt Compression | X47: Stellen suchen | Y47: https://careers.burckhardtcompression.com/search/
A48: 47 | B48: 1 | C48: Accelleron | D48: Baden | E48: AG | F48: Maschinenbau | G48: Turbolader und Einspritzsysteme für Grossmotoren | H48: 1263 | I48: USD | J48: =IF(H48="","",H48*IF(I48="CHF",1,IF(I48="EUR",'Legende & Kriterien'!$C$13,'Legende & Kriterien'!$C$14))) | K48: =IF(P48="Rohstoffhandel","— Handel —",IF(J48="","k.A.",IF(J48>=5000,"A: >5 Mrd.",IF(J48>=3000,"B: 3-5 Mrd.",IF(J48>=1000,"C: 1-3 Mrd.","D: 0.1-1 Mrd."))))) | L48: 2025 | M48: 3220 | N48: SIX: ACLN | O48: publiziert | P48: im Band | Q48: ABB-Spin-off 2022 | V48: https://stockanalysis.com/quote/swx/ACLN/financials/ | W48: Accelleron | X48: Stellen suchen | Y48: https://www.jobs.ch/en/companies/125399-accelleron-industries/
A49: 48 | B49: 3 | C49: Montana Aerospace | D49: Reinach | E49: AG | F49: Aerospace/Komponenten | G49: Strukturbauteile für Luftfahrt, E-Mobilität, Energie | H49: 1015 | I49: EUR | J49: =IF(H49="","",H49*IF(I49="CHF",1,IF(I49="EUR",'Legende & Kriterien'!$C$13,'Legende & Kriterien'!$C$14))) | K49: =IF(P49="Rohstoffhandel","— Handel —",IF(J49="","k.A.",IF(J49>=5000,"A: >5 Mrd.",IF(J49>=3000,"B: 3-5 Mrd.",IF(J49>=1000,"C: 1-3 Mrd.","D: 0.1-1 Mrd."))))) | L49: 2025 | M49: 6470 | N49: SIX: AERO | O49: publiziert | P49: im Band | V49: https://stockanalysis.com/quote/swx/AERO/financials/ | W49: Montana Aerospace | X49: Stellen suchen
A50: 49 | B50: 2 | C50: Hamilton Bonaduz | D50: Bonaduz | E50: GR | F50: Laborautomation | G50: Pipettierroboter, Laborautomation, Sensoren, Beatmungsgeräte | H50: 950 | I50: CHF | J50: =IF(H50="","",H50*IF(I50="CHF",1,IF(I50="EUR",'Legende & Kriterien'!$C$13,'Legende & Kriterien'!$C$14))) | K50: =IF(P50="Rohstoffhandel","— Handel —",IF(J50="","k.A.",IF(J50>=5000,"A: >5 Mrd.",IF(J50>=3000,"B: 3-5 Mrd.",IF(J50>=1000,"C: 1-3 Mrd.","D: 0.1-1 Mrd."))))) | L50: k.A. | M50: 3000 | N50: Familienbesitz / US-Mutter | O50: geschätzt | P50: im Band | Q50: Publiziert keine Zahlen | V50: https://de.wikipedia.org/wiki/Hamilton_Bonaduz | W50: Hamilton | X50: Stellen suchen
A51: 50 | B51: 1 | C51: Landis+Gyr | D51: Cham | E51: ZG | F51: Messtechnik | G51: Intelligente Stromzähler, Smart-Grid- und Netzmanagementsysteme | H51: 1166 | I51: USD | J51: =IF(H51="","",H51*IF(I51="CHF",1,IF(I51="EUR",'Legende & Kriterien'!$C$13,'Legende & Kriterien'!$C$14))) | K51: =IF(P51="Rohstoffhandel","— Handel —",IF(J51="","k.A.",IF(J51>=5000,"A: >5 Mrd.",IF(J51>=3000,"B: 3-5 Mrd.",IF(J51>=1000,"C: 1-3 Mrd.","D: 0.1-1 Mrd."))))) | L51: 2025/26 | M51: 6060 | N51: SIX: LAND | O51: publiziert | P51: im Band | Q51: Nur fortgeführte Geschäfte; EMEA im April 2026 verkauft | V51: https://www.landisgyr.com/nam/en/home/news-media/newsroom/2026/Landis-Gyr-Announces-Q4-and-Full-Year-FY-2025-Financial-Results | W51: Landis Gyr | X51: Stellen suchen | Y51: https://careers.landisgyr.com/search/
A52: 51 | B52: 2 | C52: Schweiter Technologies | D52: Steinhausen | E52: ZG | F52: Materialien/Leichtbau | G52: Verbundplatten, Leichtbauwerkstoffe, Displaymaterialien | H52: 904.4 | I52: CHF | J52: =IF(H52="","",H52*IF(I52="CHF",1,IF(I52="EUR",'Legende & Kriterien'!$C$13,'Legende & Kriterien'!$C$14))) | K52: =IF(P52="Rohstoffhandel","— Handel —",IF(J52="","k.A.",IF(J52>=5000,"A: >5 Mrd.",IF(J52>=3000,"B: 3-5 Mrd.",IF(J52>=1000,"C: 1-3 Mrd.","D: 0.1-1 Mrd."))))) | L52: 2025 | M52: 4080 | N52: SIX: SWTQ | O52: publiziert | P52: im Band | V52: https://stockanalysis.com/quote/swx/SWTQ/financials/ | W52: Schweiter Technologies | X52: Stellen suchen
A53: 52 | B53: 1 | C53: Tecan | D53: Männedorf | E53: ZH | F53: Laborautomation | G53: Laborautomation, Pipettierroboter, OEM-Instrumente | H53: 882.5 | I53: CHF | J53: =IF(H53="","",H53*IF(I53="CHF",1,IF(I53="EUR",'Legende & Kriterien'!$C$13,'Legende & Kriterien'!$C$14))) | K53: =IF(P53="Rohstoffhandel","— Handel —",IF(J53="","k.A.",IF(J53>=5000,"A: >5 Mrd.",IF(J53>=3000,"B: 3-5 Mrd.",IF(J53>=1000,"C: 1-3 Mrd.","D: 0.1-1 Mrd."))))) | L53: 2025 | M53: 3300 | N53: SIX: TECN | O53: publiziert | P53: im Band | V53: https://stockanalysis.com/quote/swx/TECN/financials/ | W53: Tecan | X53: Stellen suchen | Y53: https://careers.tecan.com/search/
A54: 53 | B54: 1 | C54: HUBER+SUHNER | D54: Herisau | E54: AR | F54: Konnektivität | G54: Hochfrequenz-, Glasfaser- und Kabelverbindungstechnik | H54: 864.1 | I54: CHF | J54: =IF(H54="","",H54*IF(I54="CHF",1,IF(I54="EUR",'Legende & Kriterien'!$C$13,'Legende & Kriterien'!$C$14))) | K54: =IF(P54="Rohstoffhandel","— Handel —",IF(J54="","k.A.",IF(J54>=5000,"A: >5 Mrd.",IF(J54>=3000,"B: 3-5 Mrd.",IF(J54>=1000,"C: 1-3 Mrd.","D: 0.1-1 Mrd."))))) | L54: 2025 | M54: 4220 | N54: SIX: HUBN | O54: publiziert | P54: im Band | V54: https://stockanalysis.com/quote/swx/HUBN/financials/ | W54: HUBER SUHNER | X54: Stellen suchen | Y54: https://recruiting.hubersuhner.com/Jobs/All?lang=de
A55: 54 | B55: 1 | C55: Ivoclar Group | D55: Schaan | E55: FL | F55: Dental/Medtech | G55: Dentalmaterialien, Keramik und Geräte für Zahnärzte und Labore | H55: 856 | I55: CHF | J55: =IF(H55="","",H55*IF(I55="CHF",1,IF(I55="EUR",'Legende & Kriterien'!$C$13,'Legende & Kriterien'!$C$14))) | K55: =IF(P55="Rohstoffhandel","— Handel —",IF(J55="","k.A.",IF(J55>=5000,"A: >5 Mrd.",IF(J55>=3000,"B: 3-5 Mrd.",IF(J55>=1000,"C: 1-3 Mrd.","D: 0.1-1 Mrd."))))) | L55: 2023 | M55: 3700 | N55: Familie Zeller, privat | O55: veraltet | P55: Liechtenstein | V55: https://www.wirtschaftszeit.li/news/856-millionen-franken-ivoclar-gruppe-meldet-umsatz-fuer-2023/ | W55: Ivoclar Group | X55: Stellen suchen | Y55: https://www.jobs.ch/en/companies/6731-ivoclar-vivadent-ag/
A56: 55 | B56: 3 | C56: Habasit | D56: Reinach | E56: BL | F56: Antriebs-/Fördertechnik | G56: Transportbänder, Antriebsriemen, Modul- und Zahnriemen | H56: 850 | I56: CHF | J56: =IF(H56="","",H56*IF(I56="CHF",1,IF(I56="EUR",'Legende & Kriterien'!$C$13,'Legende & Kriterien'!$C$14))) | K56: =IF(P56="Rohstoffhandel","— Handel —",IF(J56="","k.A.",IF(J56>=5000,"A: >5 Mrd.",IF(J56>=3000,"B: 3-5 Mrd.",IF(J56>=1000,"C: 1-3 Mrd.","D: 0.1-1 Mrd."))))) | L56: k.A. | M56: 3800 | N56: Familie Habegger (100%) | O56: geschätzt | P56: im Band | Q56: Publiziert keine Zahlen | V56: https://de.wikipedia.org/wiki/Habasit | W56: Habasit | X56: Stellen suchen
A57: 56 | B57: 3 | C57: RUAG MRO Holding | D57: Bern | E57: BE | F57: Verteidigungstechnik | G57: Instandhaltung und Systemintegration für die Schweizer Armee | H57: 825 | I57: CHF | J57: =IF(H57="","",H57*IF(I57="CHF",1,IF(I57="EUR",'Legende & Kriterien'!$C$13,'Legende & Kriterien'!$C$14))) | K57: =IF(P57="Rohstoffhandel","— Handel —",IF(J57="","k.A.",IF(J57>=5000,"A: >5 Mrd.",IF(J57>=3000,"B: 3-5 Mrd.",IF(J57>=1000,"C: 1-3 Mrd.","D: 0.1-1 Mrd."))))) | L57: 2025 | M57: 2500 | N57: Eidgenossenschaft (100%) | O57: publiziert | P57: im Band | V57: https://www.cash.ch/news/ruag-mro-steigert-umsatz-und-gewinn-deutlich-922782 | W57: RUAG | X57: Stellen suchen
A58: 57 | B58: 1 | C58: Kardex | D58: Zürich | E58: ZH | F58: Intralogistik/Automation | G58: Automatisierte Lager- und Kommissioniersysteme, Lagerlifte | H58: 850.4 | I58: EUR | J58: =IF(H58="","",H58*IF(I58="CHF",1,IF(I58="EUR",'Legende & Kriterien'!$C$13,'Legende & Kriterien'!$C$14))) | K58: =IF(P58="Rohstoffhandel","— Handel —",IF(J58="","k.A.",IF(J58>=5000,"A: >5 Mrd.",IF(J58>=3000,"B: 3-5 Mrd.",IF(J58>=1000,"C: 1-3 Mrd.","D: 0.1-1 Mrd."))))) | L58: 2025 | M58: 3040 | N58: SIX: KARN | O58: publiziert | P58: im Band | V58: https://stockanalysis.com/quote/swx/KARN/financials/ | W58: Kardex | X58: Stellen suchen | Y58: https://kardex.wd103.myworkdayjobs.com/Kardex — nicht abrufbar ohne Rendern, Workday
A59: 58 | B59: 3 | C59: Vetropack | D59: Bülach | E59: ZH | F59: Verpackung | G59: Glasverpackungen für Getränke und Lebensmittel | H59: 784.2 | I59: CHF | J59: =IF(H59="","",H59*IF(I59="CHF",1,IF(I59="EUR",'Legende & Kriterien'!$C$13,'Legende & Kriterien'!$C$14))) | K59: =IF(P59="Rohstoffhandel","— Handel —",IF(J59="","k.A.",IF(J59>=5000,"A: >5 Mrd.",IF(J59>=3000,"B: 3-5 Mrd.",IF(J59>=1000,"C: 1-3 Mrd.","D: 0.1-1 Mrd."))))) | L59: 2025 | M59: 3530 | N59: SIX: VETN | O59: publiziert | P59: im Band | V59: https://stockanalysis.com/quote/swx/VETN/financials/ | W59: Vetropack | X59: Stellen suchen
A60: 59 | B60: 2 | C60: Ypsomed | D60: Burgdorf | E60: BE | F60: Medtech | G60: Autoinjektoren, Pens und Pumpen zur Medikamentenabgabe | H60: 731 | I60: CHF | J60: =IF(H60="","",H60*IF(I60="CHF",1,IF(I60="EUR",'Legende & Kriterien'!$C$13,'Legende & Kriterien'!$C$14))) | K60: =IF(P60="Rohstoffhandel","— Handel —",IF(J60="","k.A.",IF(J60>=5000,"A: >5 Mrd.",IF(J60>=3000,"B: 3-5 Mrd.",IF(J60>=1000,"C: 1-3 Mrd.","D: 0.1-1 Mrd."))))) | L60: 2025/26 | M60: 2030 | N60: SIX: YPSN | O60: publiziert | P60: im Band | V60: https://stockanalysis.com/quote/swx/YPSN/financials/ | W60: Ypsomed | X60: Stellen suchen
A61: 60 | B61: 2 | C61: Zehnder Group | D61: Gränichen | E61: AG | F61: Bautechnik/HLK | G61: Komfortlüftung, Designheizkörper, Raumklimasysteme | H61: 763.3 | I61: EUR | J61: =IF(H61="","",H61*IF(I61="CHF",1,IF(I61="EUR",'Legende & Kriterien'!$C$13,'Legende & Kriterien'!$C$14))) | K61: =IF(P61="Rohstoffhandel","— Handel —",IF(J61="","k.A.",IF(J61>=5000,"A: >5 Mrd.",IF(J61>=3000,"B: 3-5 Mrd.",IF(J61>=1000,"C: 1-3 Mrd.","D: 0.1-1 Mrd."))))) | L61: 2025 | M61: 3640 | N61: SIX: ZEHN | O61: publiziert | P61: im Band | V61: https://stockanalysis.com/quote/swx/ZEHN/financials/ | W61: Zehnder | X61: Stellen suchen
A62: 61 | B62: 2 | C62: Phoenix Mecano | D62: Stein am Rhein | E62: SH | F62: Elektronik/Komponenten | G62: Industriegehäuse, Elektromechanik, elektrische Linearantriebe | H62: 748.9 | I62: EUR | J62: =IF(H62="","",H62*IF(I62="CHF",1,IF(I62="EUR",'Legende & Kriterien'!$C$13,'Legende & Kriterien'!$C$14))) | K62: =IF(P62="Rohstoffhandel","— Handel —",IF(J62="","k.A.",IF(J62>=5000,"A: >5 Mrd.",IF(J62>=3000,"B: 3-5 Mrd.",IF(J62>=1000,"C: 1-3 Mrd.","D: 0.1-1 Mrd."))))) | L62: 2025 | M62: 8100 | N62: SIX: PMN | O62: publiziert | P62: im Band | V62: https://stockanalysis.com/quote/swx/PMN/financials/ | W62: Phoenix Mecano | X62: Stellen suchen
A63: 62 | B63: 1 | C63: Rieter | D63: Winterthur | E63: ZH | F63: Textilmaschinen | G63: Spinnereimaschinen, Systeme und Komponenten | H63: 685.1 | I63: CHF | J63: =IF(H63="","",H63*IF(I63="CHF",1,IF(I63="EUR",'Legende & Kriterien'!$C$13,'Legende & Kriterien'!$C$14))) | K63: =IF(P63="Rohstoffhandel","— Handel —",IF(J63="","k.A.",IF(J63>=5000,"A: >5 Mrd.",IF(J63>=3000,"B: 3-5 Mrd.",IF(J63>=1000,"C: 1-3 Mrd.","D: 0.1-1 Mrd."))))) | L63: 2025 | M63: 6380 | N63: SIX: RIEN | O63: publiziert | P63: im Band | V63: https://stockanalysis.com/quote/swx/RIEN/financials/ | W63: Rieter | X63: Stellen suchen | Y63: https://live.solique.ch/rieter/en/internet
A64: 63 | B64: 2 | C64: Jura Elektroapparate | D64: Niederbuchsiten | E64: SO | F64: Gerätetechnik | G64: Kaffeevollautomaten für Haushalt und Büro | H64: 658.3 | I64: CHF | J64: =IF(H64="","",H64*IF(I64="CHF",1,IF(I64="EUR",'Legende & Kriterien'!$C$13,'Legende & Kriterien'!$C$14))) | K64: =IF(P64="Rohstoffhandel","— Handel —",IF(J64="","k.A.",IF(J64>=5000,"A: >5 Mrd.",IF(J64>=3000,"B: 3-5 Mrd.",IF(J64>=1000,"C: 1-3 Mrd.","D: 0.1-1 Mrd."))))) | L64: 2023 | M64: 800 | N64: Privat (Familie/Management) | O64: veraltet | P64: im Band | V64: https://www.cetoday.ch/elektro/2024-05-13/jura-investiert-in-innovation-design-und-service | W64: Jura Elektroapparate | X64: Stellen suchen
A65: 64 | B65: 2 | C65: Feintool | D65: Lyss | E65: BE | F65: Umformtechnik | G65: Feinschneidteile, Elektroblech-Stanzpakete, Pressen | H65: 656.3 | I65: CHF | J65: =IF(H65="","",H65*IF(I65="CHF",1,IF(I65="EUR",'Legende & Kriterien'!$C$13,'Legende & Kriterien'!$C$14))) | K65: =IF(P65="Rohstoffhandel","— Handel —",IF(J65="","k.A.",IF(J65>=5000,"A: >5 Mrd.",IF(J65>=3000,"B: 3-5 Mrd.",IF(J65>=1000,"C: 1-3 Mrd.","D: 0.1-1 Mrd."))))) | L65: 2025 | M65: 2940 | N65: SIX: FTON | O65: publiziert | P65: im Band | V65: https://stockanalysis.com/quote/swx/FTON/financials/ | W65: Feintool | X65: Stellen suchen
A66: 65 | B66: 2 | C66: SAUTER Group | D66: Basel | E66: BS | F66: Gebäudetechnik | G66: Gebäudeautomation: Regler, Sensoren, Ventile, Antriebe | H66: 692 | I66: EUR | J66: =IF(H66="","",H66*IF(I66="CHF",1,IF(I66="EUR",'Legende & Kriterien'!$C$13,'Legende & Kriterien'!$C$14))) | K66: =IF(P66="Rohstoffhandel","— Handel —",IF(J66="","k.A.",IF(J66>=5000,"A: >5 Mrd.",IF(J66>=3000,"B: 3-5 Mrd.",IF(J66>=1000,"C: 1-3 Mrd.","D: 0.1-1 Mrd."))))) | L66: k.A. | M66: 3387 | N66: Familie Sauter | O66: geschätzt | P66: im Band | V66: https://www.sauter-controls.com/ | W66: Sauter | X66: Stellen suchen
A67: 66 | B67: 2 | C67: Arbonia | D67: Arbon | E67: TG | F67: Bautechnik | G67: Innen- und Funktionstüren, Bauglas, Dachfenster | H67: 624.5 | I67: CHF | J67: =IF(H67="","",H67*IF(I67="CHF",1,IF(I67="EUR",'Legende & Kriterien'!$C$13,'Legende & Kriterien'!$C$14))) | K67: =IF(P67="Rohstoffhandel","— Handel —",IF(J67="","k.A.",IF(J67>=5000,"A: >5 Mrd.",IF(J67>=3000,"B: 3-5 Mrd.",IF(J67>=1000,"C: 1-3 Mrd.","D: 0.1-1 Mrd."))))) | L67: 2025 | M67: 3600 | N67: SIX: ARBN | O67: publiziert | P67: im Band | V67: https://www.cash.ch/news/top-news/arbonia-steigert-2025-umsatz-und-weist-verlust-aus-914119 | W67: Arbonia | X67: Stellen suchen
A68: 67 | B68: 3 | C68: Eugster/Frismag | D68: Amriswil | E68: TG | F68: Gerätetechnik OEM | G68: OEM-Kaffeevollautomaten und Haushaltgeräte für Fremdmarken | H68: 620 | I68: CHF | J68: =IF(H68="","",H68*IF(I68="CHF",1,IF(I68="EUR",'Legende & Kriterien'!$C$13,'Legende & Kriterien'!$C$14))) | K68: =IF(P68="Rohstoffhandel","— Handel —",IF(J68="","k.A.",IF(J68>=5000,"A: >5 Mrd.",IF(J68>=3000,"B: 3-5 Mrd.",IF(J68>=1000,"C: 1-3 Mrd.","D: 0.1-1 Mrd."))))) | L68: 2021 | M68: 3600 | N68: Familie Eugster (100%) | O68: veraltet | P68: im Band | V68: https://dewiki.de/Lexikon/Eugster/Frismag | W68: Eugster Frismag | X68: Stellen suchen
A69: 68 | B69: 2 | C69: Cicor | D69: Bronschhofen (Wil) | E69: SG | F69: Elektronik/EMS | G69: Elektronikfertigung, Leiterplatten, Mikroelektronik | H69: 616.5 | I69: CHF | J69: =IF(H69="","",H69*IF(I69="CHF",1,IF(I69="EUR",'Legende & Kriterien'!$C$13,'Legende & Kriterien'!$C$14))) | K69: =IF(P69="Rohstoffhandel","— Handel —",IF(J69="","k.A.",IF(J69>=5000,"A: >5 Mrd.",IF(J69>=3000,"B: 3-5 Mrd.",IF(J69>=1000,"C: 1-3 Mrd.","D: 0.1-1 Mrd."))))) | L69: 2025 | M69: 4520 | N69: SIX: CICN | O69: publiziert | P69: im Band | V69: https://report.cicor.com/ar25/key-figures | W69: Cicor | X69: Stellen suchen
A70: 69 | B70: 2 | C70: Bystronic | D70: Niederönz | E70: BE | F70: Werkzeugmaschinen | G70: Laserschneidanlagen, Abkantpressen, Automation Blech | H70: 613.2 | I70: CHF | J70: =IF(H70="","",H70*IF(I70="CHF",1,IF(I70="EUR",'Legende & Kriterien'!$C$13,'Legende & Kriterien'!$C$14))) | K70: =IF(P70="Rohstoffhandel","— Handel —",IF(J70="","k.A.",IF(J70>=5000,"A: >5 Mrd.",IF(J70>=3000,"B: 3-5 Mrd.",IF(J70>=1000,"C: 1-3 Mrd.","D: 0.1-1 Mrd."))))) | L70: 2025 | M70: 3060 | N70: SIX: BYS | O70: publiziert | P70: im Band | V70: https://mtdcnc.com/news/bystronic/bystronic-reports-strong-2025-results-despite-economic-challenges/ | W70: Bystronic | X70: Stellen suchen
A71: 70 | B71: 3 | C71: Medela | D71: Baar | E71: ZG | F71: Medtech | G71: Milchpumpen, medizinische Vakuumtechnik, Wundtherapie | H71: 600 | I71: CHF | J71: =IF(H71="","",H71*IF(I71="CHF",1,IF(I71="EUR",'Legende & Kriterien'!$C$13,'Legende & Kriterien'!$C$14))) | K71: =IF(P71="Rohstoffhandel","— Handel —",IF(J71="","k.A.",IF(J71>=5000,"A: >5 Mrd.",IF(J71>=3000,"B: 3-5 Mrd.",IF(J71>=1000,"C: 1-3 Mrd.","D: 0.1-1 Mrd."))))) | L71: k.A. | M71: 1700 | N71: Familie Larsson (100%) | O71: geschätzt | P71: im Band | Q71: Publiziert keine Zahlen | V71: https://de.wikipedia.org/wiki/Medela | W71: Medela | X71: Stellen suchen
A72: 71 | B72: 1 | C72: maxon group | D72: Sachseln | E72: OW | F72: Antriebstechnik | G72: Präzisions-Kleinantriebe, Getriebe, Steuerungen, Mechatronik | H72: 595 | I72: CHF | J72: =IF(H72="","",H72*IF(I72="CHF",1,IF(I72="EUR",'Legende & Kriterien'!$C$13,'Legende & Kriterien'!$C$14))) | K72: =IF(P72="Rohstoffhandel","— Handel —",IF(J72="","k.A.",IF(J72>=5000,"A: >5 Mrd.",IF(J72>=3000,"B: 3-5 Mrd.",IF(J72>=1000,"C: 1-3 Mrd.","D: 0.1-1 Mrd."))))) | L72: 2025 | M72: 3500 | N72: Familie Braun (Interelectric) | O72: publiziert | P72: im Band | V72: https://www.cash.ch/news/maxon-halt-umsatz-stabil-neue-prasidentin-947917 | W72: maxon motor | X72: Stellen suchen | Y72: https://recruiting.maxongroup.com/Jobs/All?lang=de
A73: 72 | B73: 1 | C73: Komax | D73: Dierikon | E73: LU | F73: Automation/Maschinenbau | G73: Maschinen für Kabelverarbeitung und Kabelbaumfertigung | H73: 575.6 | I73: CHF | J73: =IF(H73="","",H73*IF(I73="CHF",1,IF(I73="EUR",'Legende & Kriterien'!$C$13,'Legende & Kriterien'!$C$14))) | K73: =IF(P73="Rohstoffhandel","— Handel —",IF(J73="","k.A.",IF(J73>=5000,"A: >5 Mrd.",IF(J73>=3000,"B: 3-5 Mrd.",IF(J73>=1000,"C: 1-3 Mrd.","D: 0.1-1 Mrd."))))) | L73: 2025 | M73: 3030 | N73: SIX: KOMN | O73: publiziert | P73: im Band | V73: https://stockanalysis.com/quote/swx/KOMN/financials/ | W73: Komax | X73: Stellen suchen | Y73: https://www.jobs.ch/de/firmen/791-komax-group/stellenangebote/
A74: 73 | B74: 2 | C74: V-ZUG | D74: Zug | E74: ZG | F74: Hausgerätetechnik | G74: Küchen- und Waschraumgeräte: Backöfen, Steamer, Waschmaschinen | H74: 567.5 | I74: CHF | J74: =IF(H74="","",H74*IF(I74="CHF",1,IF(I74="EUR",'Legende & Kriterien'!$C$13,'Legende & Kriterien'!$C$14))) | K74: =IF(P74="Rohstoffhandel","— Handel —",IF(J74="","k.A.",IF(J74>=5000,"A: >5 Mrd.",IF(J74>=3000,"B: 3-5 Mrd.",IF(J74>=1000,"C: 1-3 Mrd.","D: 0.1-1 Mrd."))))) | L74: 2025 | M74: 2040 | N74: SIX: VZUG | O74: publiziert | P74: im Band | V74: https://stockanalysis.com/quote/swx/VZUG/financials/ | W74: V-ZUG | X74: Stellen suchen
A75: 74 | B75: 3 | C75: Acrotec Group | D75: Delémont | E75: JU | F75: Präzisionsfertigung | G75: Hochpräzisionsteile für Uhren, Medtech, Mikromechanik | H75: 550 | I75: CHF | J75: =IF(H75="","",H75*IF(I75="CHF",1,IF(I75="EUR",'Legende & Kriterien'!$C$13,'Legende & Kriterien'!$C$14))) | K75: =IF(P75="Rohstoffhandel","— Handel —",IF(J75="","k.A.",IF(J75>=5000,"A: >5 Mrd.",IF(J75>=3000,"B: 3-5 Mrd.",IF(J75>=1000,"C: 1-3 Mrd.","D: 0.1-1 Mrd."))))) | L75: 2022 | M75: 2600 | N75: Private Equity: Carlyle | O75: geschätzt | P75: im Band | V75: https://www.cash.ch/borsen-ticker/unternehmen/acrotec-knackt-500-millionen-schwelle-beim-umsatz-562189 | W75: Acrotec | X75: Stellen suchen
A76: 75 | B76: 2 | C76: INFICON | D76: Bad Ragaz | E76: SG | F76: Sensorik/Messtechnik | G76: Vakuum-Messgeräte, Lecksucher, Prozessüberwachung Halbleiter | H76: 673.7 | I76: USD | J76: =IF(H76="","",H76*IF(I76="CHF",1,IF(I76="EUR",'Legende & Kriterien'!$C$13,'Legende & Kriterien'!$C$14))) | K76: =IF(P76="Rohstoffhandel","— Handel —",IF(J76="","k.A.",IF(J76>=5000,"A: >5 Mrd.",IF(J76>=3000,"B: 3-5 Mrd.",IF(J76>=1000,"C: 1-3 Mrd.","D: 0.1-1 Mrd."))))) | L76: 2025 | M76: 1730 | N76: SIX: IFCN | O76: publiziert | P76: im Band | V76: https://stockanalysis.com/quote/swx/IFCN/financials/ | W76: INFICON | X76: Stellen suchen
A77: 76 | B77: 1 | C77: Baumer Group | D77: Frauenfeld | E77: TG | F77: Sensorik/Automation | G77: Sensoren, Drehgeber, Prozessinstrumente, Bildverarbeitung | H77: 520 | I77: CHF | J77: =IF(H77="","",H77*IF(I77="CHF",1,IF(I77="EUR",'Legende & Kriterien'!$C$13,'Legende & Kriterien'!$C$14))) | K77: =IF(P77="Rohstoffhandel","— Handel —",IF(J77="","k.A.",IF(J77>=5000,"A: >5 Mrd.",IF(J77>=3000,"B: 3-5 Mrd.",IF(J77>=1000,"C: 1-3 Mrd.","D: 0.1-1 Mrd."))))) | L77: 2022 | M77: 2800 | N77: Familie Vietze (100%) | O77: veraltet | P77: im Band | V77: https://de.wikipedia.org/wiki/Baumer_Group | W77: Baumer | X77: Stellen suchen | Y77: https://jobs.baumer.com/ — nicht abrufbar ohne Rendern, Prospective-Widget
A78: 77 | B78: 1 | C78: Interroll | D78: Sant'Antonino | E78: TI | F78: Intralogistik | G78: Rollen, Motorrollen, Förderer und Sorter für Materialfluss | H78: 514.2 | I78: CHF | J78: =IF(H78="","",H78*IF(I78="CHF",1,IF(I78="EUR",'Legende & Kriterien'!$C$13,'Legende & Kriterien'!$C$14))) | K78: =IF(P78="Rohstoffhandel","— Handel —",IF(J78="","k.A.",IF(J78>=5000,"A: >5 Mrd.",IF(J78>=3000,"B: 3-5 Mrd.",IF(J78>=1000,"C: 1-3 Mrd.","D: 0.1-1 Mrd."))))) | L78: 2025 | M78: 2400 | N78: SIX: INRN | O78: publiziert | P78: im Band | V78: https://www.interroll.com/news-events/press-releases | W78: Interroll | X78: Stellen suchen | Y78: https://www.interroll.com/company/careers/
A79: 78 | B79: 1 | C79: Meier Tobler | D79: Schwerzenbach | E79: ZH | F79: Bautechnik/HLK | G79: Wärmepumpen, Heiz- und Klimasysteme, Service | H79: 496.6 | I79: CHF | J79: =IF(H79="","",H79*IF(I79="CHF",1,IF(I79="EUR",'Legende & Kriterien'!$C$13,'Legende & Kriterien'!$C$14))) | K79: =IF(P79="Rohstoffhandel","— Handel —",IF(J79="","k.A.",IF(J79>=5000,"A: >5 Mrd.",IF(J79>=3000,"B: 3-5 Mrd.",IF(J79>=1000,"C: 1-3 Mrd.","D: 0.1-1 Mrd."))))) | L79: 2025 | M79: 1260 | N79: SIX: MTG | O79: publiziert | P79: im Band | V79: https://stockanalysis.com/quote/swx/MTG/financials/ | W79: Meier Tobler | X79: Stellen suchen | Y79: https://www.jobs.ch/en/companies/85876-meier-tobler-ag/vacancies/
A80: 79 | B80: 1 | C80: Kistler Gruppe | D80: Winterthur | E80: ZH | F80: Sensorik/Messtechnik | G80: Piezoelektrische Sensoren für Druck, Kraft, Drehmoment | H80: 465 | I80: CHF | J80: =IF(H80="","",H80*IF(I80="CHF",1,IF(I80="EUR",'Legende & Kriterien'!$C$13,'Legende & Kriterien'!$C$14))) | K80: =IF(P80="Rohstoffhandel","— Handel —",IF(J80="","k.A.",IF(J80>=5000,"A: >5 Mrd.",IF(J80>=3000,"B: 3-5 Mrd.",IF(J80>=1000,"C: 1-3 Mrd.","D: 0.1-1 Mrd."))))) | L80: 2023 | M80: 2200 | N80: Familie Sonderegger | O80: veraltet | P80: im Band | V80: https://de.wikipedia.org/wiki/Kistler_Gruppe | W80: Kistler | X80: Stellen suchen | Y80: https://www.kistler.com/CH/de/kistler-stellenangebote/jobs
A81: 80 | B81: 3 | C81: Comet Group | D81: Flamatt | E81: FR | F81: Halbleiter/Elektronik | G81: HF-Generatoren, Vakuumkondensatoren, Röntgenmodule | H81: 457 | I81: CHF | J81: =IF(H81="","",H81*IF(I81="CHF",1,IF(I81="EUR",'Legende & Kriterien'!$C$13,'Legende & Kriterien'!$C$14))) | K81: =IF(P81="Rohstoffhandel","— Handel —",IF(J81="","k.A.",IF(J81>=5000,"A: >5 Mrd.",IF(J81>=3000,"B: 3-5 Mrd.",IF(J81>=1000,"C: 1-3 Mrd.","D: 0.1-1 Mrd."))))) | L81: 2025 | M81: 1760 | N81: SIX: COTN | O81: publiziert | P81: im Band | V81: https://stockanalysis.com/quote/swx/COTN/financials/ | W81: Comet | X81: Stellen suchen
A82: 81 | B82: 2 | C82: medmix | D82: Baar | E82: ZG | F82: Medtech/Komponenten | G82: Präzisions-Applikations- und Mischsysteme | H82: 448 | I82: CHF | J82: =IF(H82="","",H82*IF(I82="CHF",1,IF(I82="EUR",'Legende & Kriterien'!$C$13,'Legende & Kriterien'!$C$14))) | K82: =IF(P82="Rohstoffhandel","— Handel —",IF(J82="","k.A.",IF(J82>=5000,"A: >5 Mrd.",IF(J82>=3000,"B: 3-5 Mrd.",IF(J82>=1000,"C: 1-3 Mrd.","D: 0.1-1 Mrd."))))) | L82: 2025 | M82: 2590 | N82: SIX: MEDX | O82: publiziert | P82: im Band | V82: https://stockanalysis.com/quote/swx/MEDX/financials/ | W82: medmix | X82: Stellen suchen
A83: 82 | B83: 3 | C83: StarragTornos | D83: Rorschacherberg | E83: SG | F83: Werkzeugmaschinen | G83: Präzisions-Werkzeugmaschinen, Fräs- und Drehautomaten | H83: 442.1 | I83: CHF | J83: =IF(H83="","",H83*IF(I83="CHF",1,IF(I83="EUR",'Legende & Kriterien'!$C$13,'Legende & Kriterien'!$C$14))) | K83: =IF(P83="Rohstoffhandel","— Handel —",IF(J83="","k.A.",IF(J83>=5000,"A: >5 Mrd.",IF(J83>=3000,"B: 3-5 Mrd.",IF(J83>=1000,"C: 1-3 Mrd.","D: 0.1-1 Mrd."))))) | L83: 2025 | M83: 1800 | N83: SIX: STGN | O83: publiziert | P83: im Band | Q83: Fusion Starrag/Tornos | V83: https://stockanalysis.com/quote/swx/STGN/financials/ | W83: StarragTornos | X83: Stellen suchen
A84: 83 | B84: 1 | C84: Reishauer | D84: Wallisellen | E84: ZH | F84: Werkzeugmaschinen | G84: Verzahnungsschleifmaschinen, Schleifwerkzeuge, Automation | H84: 431 | I84: CHF | J84: =IF(H84="","",H84*IF(I84="CHF",1,IF(I84="EUR",'Legende & Kriterien'!$C$13,'Legende & Kriterien'!$C$14))) | K84: =IF(P84="Rohstoffhandel","— Handel —",IF(J84="","k.A.",IF(J84>=5000,"A: >5 Mrd.",IF(J84>=3000,"B: 3-5 Mrd.",IF(J84>=1000,"C: 1-3 Mrd.","D: 0.1-1 Mrd."))))) | L84: 2023 | M84: 1654 | N84: Familie / OTC-X | O84: veraltet | P84: im Band | V84: https://www.reishauer.com/ | W84: Reishauer | X84: Stellen suchen | Y84: https://jobs.reishauer.com/search/?locale=de_DE
A85: 84 | B85: 3 | C85: R&S Group | D85: Sissach | E85: BL | F85: Energieinfrastruktur | G85: Transformatoren, Schaltanlagen, Bahnelektrifizierung | H85: 414.8 | I85: CHF | J85: =IF(H85="","",H85*IF(I85="CHF",1,IF(I85="EUR",'Legende & Kriterien'!$C$13,'Legende & Kriterien'!$C$14))) | K85: =IF(P85="Rohstoffhandel","— Handel —",IF(J85="","k.A.",IF(J85>=5000,"A: >5 Mrd.",IF(J85>=3000,"B: 3-5 Mrd.",IF(J85>=1000,"C: 1-3 Mrd.","D: 0.1-1 Mrd."))))) | L85: 2025 | M85: 1330 | N85: SIX: RSGN | O85: publiziert | P85: im Band | V85: https://stockanalysis.com/quote/swx/RSGN/financials/ | W85: R&S Group | X85: Stellen suchen
A86: 85 | B86: 2 | C86: Beyond Gravity | D86: Zürich | E86: ZH | F86: Raumfahrt | G86: Strukturen, Nutzlastverkleidungen, Elektronik für Raumfahrt | H86: 412 | I86: CHF | J86: =IF(H86="","",H86*IF(I86="CHF",1,IF(I86="EUR",'Legende & Kriterien'!$C$13,'Legende & Kriterien'!$C$14))) | K86: =IF(P86="Rohstoffhandel","— Handel —",IF(J86="","k.A.",IF(J86>=5000,"A: >5 Mrd.",IF(J86>=3000,"B: 3-5 Mrd.",IF(J86>=1000,"C: 1-3 Mrd.","D: 0.1-1 Mrd."))))) | L86: 2025 | M86: 1926 | N86: Eidgenossenschaft (100%) | O86: publiziert | P86: im Band | V86: https://www.beyondgravity.com/en/annual-report-2025 | W86: Beyond Gravity | X86: Stellen suchen
A87: 86 | B87: 3 | C87: Victorinox | D87: Ibach-Schwyz | E87: SZ | F87: Konsum-/Präzisionsgüter | G87: Taschenmesser, Küchenmesser, Uhren, Reisegepäck | H87: 404 | I87: CHF | J87: =IF(H87="","",H87*IF(I87="CHF",1,IF(I87="EUR",'Legende & Kriterien'!$C$13,'Legende & Kriterien'!$C$14))) | K87: =IF(P87="Rohstoffhandel","— Handel —",IF(J87="","k.A.",IF(J87>=5000,"A: >5 Mrd.",IF(J87>=3000,"B: 3-5 Mrd.",IF(J87>=1000,"C: 1-3 Mrd.","D: 0.1-1 Mrd."))))) | L87: 2025 | M87: 2000 | N87: Stiftung + Familie Elsener | O87: publiziert | P87: im Band | V87: https://www.bote.ch/nachrichten/schwyz/victorinox-leidet-unter-zoellen-und-starkem-franken-art-1686763 | W87: Victorinox | X87: Stellen suchen
A88: 87 | B88: 3 | C88: Rheinmetall Air Defence | D88: Zürich-Oerlikon | E88: ZH | F88: Verteidigungstechnik | G88: Flugabwehrsysteme, Feuerleitsysteme, AHEAD-Munition | H88: 400 | I88: CHF | J88: =IF(H88="","",H88*IF(I88="CHF",1,IF(I88="EUR",'Legende & Kriterien'!$C$13,'Legende & Kriterien'!$C$14))) | K88: =IF(P88="Rohstoffhandel","— Handel —",IF(J88="","k.A.",IF(J88>=5000,"A: >5 Mrd.",IF(J88>=3000,"B: 3-5 Mrd.",IF(J88>=1000,"C: 1-3 Mrd.","D: 0.1-1 Mrd."))))) | L88: k.A. | M88: 900 | N88: Rheinmetall AG (DE) | O88: geschätzt | P88: im Band | Q88: CH-Standort eines DE-Konzerns | V88: https://www.find-your-future.ch/de/arbeiten-mem-branche/branche-unternehmen/firmenportraits/rheinmetall-air-defence/ | W88: Rheinmetall | X88: Stellen suchen
A89: 88 | B89: 3 | C89: GDELS-Mowag | D89: Kreuzlingen | E89: TG | F89: Verteidigungstechnik | G89: Geschützte Radfahrzeuge PIRANHA, EAGLE, DURO | H89: 400 | I89: CHF | J89: =IF(H89="","",H89*IF(I89="CHF",1,IF(I89="EUR",'Legende & Kriterien'!$C$13,'Legende & Kriterien'!$C$14))) | K89: =IF(P89="Rohstoffhandel","— Handel —",IF(J89="","k.A.",IF(J89>=5000,"A: >5 Mrd.",IF(J89>=3000,"B: 3-5 Mrd.",IF(J89>=1000,"C: 1-3 Mrd.","D: 0.1-1 Mrd."))))) | L89: k.A. | M89: 800 | N89: General Dynamics (US) | O89: geschätzt | P89: im Band | Q89: CH-Standort eines US-Konzerns | V89: https://www.find-your-future.ch/de/arbeiten-mem-branche/branche-unternehmen/firmenportraits/gdels-mowag-gmbh/ | W89: Mowag | X89: Stellen suchen
A90: 89 | B90: 3 | C90: Mikron | D90: Agno | E90: TI | F90: Automation/Maschinenbau | G90: Montage- und Prüfautomation, Präzisionsdrehteile | H90: 381.9 | I90: CHF | J90: =IF(H90="","",H90*IF(I90="CHF",1,IF(I90="EUR",'Legende & Kriterien'!$C$13,'Legende & Kriterien'!$C$14))) | K90: =IF(P90="Rohstoffhandel","— Handel —",IF(J90="","k.A.",IF(J90>=5000,"A: >5 Mrd.",IF(J90>=3000,"B: 3-5 Mrd.",IF(J90>=1000,"C: 1-3 Mrd.","D: 0.1-1 Mrd."))))) | L90: 2025 | M90: 1530 | N90: SIX: MIKN | O90: publiziert | P90: im Band | V90: https://stockanalysis.com/quote/swx/MIKN/financials/ | W90: Mikron | X90: Stellen suchen
A91: 90 | B91: 3 | C91: Griesser | D91: Aadorf | E91: TG | F91: Gebäudetechnik/Sonnenschutz | G91: Sonnenstoren, Raffstoren, Rollläden, Terrassendächer | H91: 370 | I91: CHF | J91: =IF(H91="","",H91*IF(I91="CHF",1,IF(I91="EUR",'Legende & Kriterien'!$C$13,'Legende & Kriterien'!$C$14))) | K91: =IF(P91="Rohstoffhandel","— Handel —",IF(J91="","k.A.",IF(J91>=5000,"A: >5 Mrd.",IF(J91>=3000,"B: 3-5 Mrd.",IF(J91>=1000,"C: 1-3 Mrd.","D: 0.1-1 Mrd."))))) | L91: 2021 | M91: 1500 | N91: Familienbesitz / OTC-X | O91: veraltet | P91: im Band | V91: https://de.wikipedia.org/wiki/Griesser_Holding | W91: Griesser | X91: Stellen suchen
A92: 91 | B92: 3 | C92: Aluflexpack | D92: Reinach | E92: AG | F92: Verpackung | G92: Flexible Verpackungen aus Aluminium und Folien für Food und Pharma | H92: 374.9 | I92: EUR | J92: =IF(H92="","",H92*IF(I92="CHF",1,IF(I92="EUR",'Legende & Kriterien'!$C$13,'Legende & Kriterien'!$C$14))) | K92: =IF(P92="Rohstoffhandel","— Handel —",IF(J92="","k.A.",IF(J92>=5000,"A: >5 Mrd.",IF(J92>=3000,"B: 3-5 Mrd.",IF(J92>=1000,"C: 1-3 Mrd.","D: 0.1-1 Mrd."))))) | L92: 2024 | M92: 1674 | N92: Constantia Flexibles / One Rock | O92: veraltet | P92: im Band | Q92: Delisting SIX 11.07.2025; keine Publikation mehr | V92: https://www.cflex.com/ | W92: Aluflexpack | X92: Stellen suchen
A93: 92 | B93: 3 | C93: Sonceboz | D93: Sonceboz-Sombeval | E93: BE | F93: Mechatronik | G93: Mechatronische Aktuatoren und Motoren für Auto, Industrie, Medtech | H93: 350 | I93: CHF | J93: =IF(H93="","",H93*IF(I93="CHF",1,IF(I93="EUR",'Legende & Kriterien'!$C$13,'Legende & Kriterien'!$C$14))) | K93: =IF(P93="Rohstoffhandel","— Handel —",IF(J93="","k.A.",IF(J93>=5000,"A: >5 Mrd.",IF(J93>=3000,"B: 3-5 Mrd.",IF(J93>=1000,"C: 1-3 Mrd.","D: 0.1-1 Mrd."))))) | L93: k.A. | M93: 1500 | N93: Familienunternehmen | O93: geschätzt | P93: im Band | V93: https://sonceboz.com/about-us/ | W93: Sonceboz | X93: Stellen suchen
A94: 93 | B94: 1 | C94: Sensirion | D94: Stäfa | E94: ZH | F94: Sensorik | G94: Umwelt- und Flusssensoren, CMOS-Sensormodule | H94: 342.4 | I94: CHF | J94: =IF(H94="","",H94*IF(I94="CHF",1,IF(I94="EUR",'Legende & Kriterien'!$C$13,'Legende & Kriterien'!$C$14))) | K94: =IF(P94="Rohstoffhandel","— Handel —",IF(J94="","k.A.",IF(J94>=5000,"A: >5 Mrd.",IF(J94>=3000,"B: 3-5 Mrd.",IF(J94>=1000,"C: 1-3 Mrd.","D: 0.1-1 Mrd."))))) | L94: 2025 | M94: 1310 | N94: SIX: SENS | O94: publiziert | P94: im Band | Q94: Dein früherer Arbeitgeber | V94: https://stockanalysis.com/quote/swx/SENS/financials/ | W94: Sensirion | X94: Stellen suchen | Y94: https://sensirion.com/career
A95: 94 | B95: 2 | C95: Weidmann Holding (WICOR) | D95: Rapperswil-Jona | E95: SG | F95: Elektrotechnik/Medtech | G95: Transformator-Isolationen, Medtech-Spritzguss, MFC | H95: 341 | I95: CHF | J95: =IF(H95="","",H95*IF(I95="CHF",1,IF(I95="EUR",'Legende & Kriterien'!$C$13,'Legende & Kriterien'!$C$14))) | K95: =IF(P95="Rohstoffhandel","— Handel —",IF(J95="","k.A.",IF(J95>=5000,"A: >5 Mrd.",IF(J95>=3000,"B: 3-5 Mrd.",IF(J95>=1000,"C: 1-3 Mrd.","D: 0.1-1 Mrd."))))) | L95: 2020 | M95: 2700 | N95: Familie Weidmann/Tschudi | O95: veraltet | P95: im Band | Q95: Dürfte durch den Transformatoren-Boom deutlich höher liegen | V95: https://linth24.ch/articles/64161-weidmann-mit-umsatzrueckgang-und-expansionsplan | W95: Weidmann | X95: Stellen suchen
A96: 95 | B96: 2 | C96: SKAN Group | D96: Allschwil | E96: BL | F96: Reinraumtechnik | G96: Isolatoren und Reinraumtechnik für aseptische Pharmaproduktion | H96: 333.3 | I96: CHF | J96: =IF(H96="","",H96*IF(I96="CHF",1,IF(I96="EUR",'Legende & Kriterien'!$C$13,'Legende & Kriterien'!$C$14))) | K96: =IF(P96="Rohstoffhandel","— Handel —",IF(J96="","k.A.",IF(J96>=5000,"A: >5 Mrd.",IF(J96>=3000,"B: 3-5 Mrd.",IF(J96>=1000,"C: 1-3 Mrd.","D: 0.1-1 Mrd."))))) | L96: 2025 | M96: 1740 | N96: SIX: SKAN | O96: publiziert | P96: im Band | V96: https://stockanalysis.com/quote/swx/SKAN/financials/ | W96: SKAN | X96: Stellen suchen
A97: 96 | B97: 2 | C97: Sefar Group | D97: Thal | E97: SG | F97: Industrietextilien | G97: Präzisionsgewebe für Siebdruck, Filtration, Elektronik, Medtech | H97: 347 | I97: EUR | J97: =IF(H97="","",H97*IF(I97="CHF",1,IF(I97="EUR",'Legende & Kriterien'!$C$13,'Legende & Kriterien'!$C$14))) | K97: =IF(P97="Rohstoffhandel","— Handel —",IF(J97="","k.A.",IF(J97>=5000,"A: >5 Mrd.",IF(J97>=3000,"B: 3-5 Mrd.",IF(J97>=1000,"C: 1-3 Mrd.","D: 0.1-1 Mrd."))))) | L97: 2024 | M97: 2900 | N97: Gründerfamilie (100%) | O97: geschätzt | P97: im Band | V97: https://www.weltmarktfuehrerindex.de/profil/sefar | W97: Sefar | X97: Stellen suchen
A98: 97 | B98: 2 | C98: Gurit | D98: Wattwil | E98: SG | F98: Composites | G98: Faserverbundwerkstoffe, Strukturschaumkerne, Klebstoffe | H98: 319.6 | I98: CHF | J98: =IF(H98="","",H98*IF(I98="CHF",1,IF(I98="EUR",'Legende & Kriterien'!$C$13,'Legende & Kriterien'!$C$14))) | K98: =IF(P98="Rohstoffhandel","— Handel —",IF(J98="","k.A.",IF(J98>=5000,"A: >5 Mrd.",IF(J98>=3000,"B: 3-5 Mrd.",IF(J98>=1000,"C: 1-3 Mrd.","D: 0.1-1 Mrd."))))) | L98: 2025 | M98: 1950 | N98: SIX: GURN | O98: publiziert | P98: im Band | V98: https://stockanalysis.com/quote/swx/GURN/financials/ | W98: Gurit | X98: Stellen suchen
A99: 98 | B99: 1 | C99: Ferag (WRH) | D99: Hinwil | E99: ZH | F99: Intralogistik | G99: Materialfluss- und Hängefördersysteme, Sortierlösungen | H99: 300 | I99: CHF | J99: =IF(H99="","",H99*IF(I99="CHF",1,IF(I99="EUR",'Legende & Kriterien'!$C$13,'Legende & Kriterien'!$C$14))) | K99: =IF(P99="Rohstoffhandel","— Handel —",IF(J99="","k.A.",IF(J99>=5000,"A: >5 Mrd.",IF(J99>=3000,"B: 3-5 Mrd.",IF(J99>=1000,"C: 1-3 Mrd.","D: 0.1-1 Mrd."))))) | L99: k.A. | M99: 600 | N99: Familie Reist/Rau | O99: geschätzt | P99: im Band | V99: https://de.wikipedia.org/wiki/Ferag | W99: Ferag | X99: Stellen suchen | Y99: https://recruitingapp-2970.umantis.com/Jobs/1?CompanyID=1
A100: 99 | B100: 2 | C100: Ascom | D100: Baar | E100: ZG | F100: Kommunikationstechnik | G100: Mobile Kommunikations- und Alarmierungssysteme für Spitäler | H100: 292.1 | I100: CHF | J100: =IF(H100="","",H100*IF(I100="CHF",1,IF(I100="EUR",'Legende & Kriterien'!$C$13,'Legende & Kriterien'!$C$14))) | K100: =IF(P100="Rohstoffhandel","— Handel —",IF(J100="","k.A.",IF(J100>=5000,"A: >5 Mrd.",IF(J100>=3000,"B: 3-5 Mrd.",IF(J100>=1000,"C: 1-3 Mrd.","D: 0.1-1 Mrd."))))) | L100: 2025 | M100: 1380 | N100: SIX: ASCN | O100: publiziert | P100: im Band | V100: https://stockanalysis.com/quote/swx/ASCN/financials/ | W100: Ascom | X100: Stellen suchen
...

Sheet Legende & Kriterien
A1: Zielliste Schweizer Industrieunternehmen
A2: Stand 28.08.2026 · Kernliste nach Umsatz, danach Konzern-HQs, zuletzt Rohstoffhändler
A4: Die fünf Gruppen
A5: Kern (weiss) | B5: Eigenständige Schweizer Industrieunternehmen mit engineered product, CHF 100 Mio.–3 Mrd.
A6: Grosskonzern (grün) | B6: Schweizer Konzerne über CHF 3 Mrd.
A7: Liechtenstein (orange) | B7: Sitz im Fürstentum. Eigenes Arbeitsrecht und Sozialsystem, ab Meilen nur mit Wochenaufenthalt.
A8: Konzern-HQ CH (violett) | B8: Ausländische Gruppen, deren Schweizer Standort ein internationales Mandat hat. Spalte Q nennt das Mandat.
A9: Rohstoffhandel (grau) | B9: Kein eigenes Produkt. Umsatz ist Handelsumsatz. Nur über die Strategie- und M&A-Schiene relevant.
A11: Mandat (Spalte Q, nur bei violetten Zeilen)
A12: GLOBAL-HQ | B12: Weltzentrale des Konzerns oder der Gruppe sitzt in der Schweiz. Höchste Entscheidungsdichte.
A13: DIVISIONS-HQ | B13: Weltsitz einer einzelnen Division. Für Commercial-Rollen oft ideal: internationales Mandat, überschaubare Organisation.
A14: EMEA-HQ | B14: Europa-/Nahost-/Afrika-Zentrale. Internationales Mandat, aber die Konzernstrategie kommt aus dem Ausland.
A15: GROSSSTANDORT | B15: Grosses Werk oder Entwicklungszentrum ohne HQ-Mandat. Kommerziell meist dünn — vor allem Technik.
A17: Grössenklassen und Wechselkurse
A18: A >5 Mrd. · B 3–5 Mrd. · C 1–3 Mrd. · D 0.1–1 Mrd. Bei Konzern-HQs und Rohstoffhändlern ist die Klasse nicht aussagekräftig — dort zählt die Mitarbeiterzahl in Spalte M.
B20: EUR → CHF | C20: 0.94
B21: USD → CHF | C21: 0.8
A23: Prio-Stufen (Spalte B) — steuern den Job-Radar
A24: Prio 1 | B24: Täglich abgefragt, blau hinterlegt.
A25: Prio 2 | B25: Montag, Mittwoch, Freitag.
A26: Prio 3 | B26: Erster und dritter Dienstag. Alle Neuzugänge stehen zunächst hier.
A28: Datenqualität (Spalte O)
A29: publiziert | B29: Aus Geschäftsbericht oder Medienmitteilung des laufenden Jahres.
A30: veraltet | B30: Letzte öffentlich auffindbare Zahl, teils Jahre alt.
A31: geschätzt | B31: Firma publiziert keine Zahlen. Grössenordnung aus Branchenquellen. Nie zitieren.
A32: Handelsumsatz | B32: Nur bei Rohstoffhändlern. Durchgehandeltes Volumen, keine Wertschöpfung.
A34: Spalten zum Ausfüllen (gelb)
A35: R — Fit-Score | B35: 1–5. 5 = würde ich sofort ansprechen.
A36: S — Kontakt im Netzwerk | B36: Name, wenn du dort jemanden kennst. Die wichtigste Spalte im Blatt.
A37: T — Status | B37: offen / recherchiert / kontaktiert / beworben / abgesagt
A38: U — Notizen | B38: Auslöser, Gesprächsnotizen, offene Stellen.
A40: Was diese Liste nicht ist
A41: Ein Screening-Ausgangspunkt, keine geprüfte Datenbank. Bei den Konzern-HQs sind die Mitarbeiterzahlen meist Schätzungen, und ein Mandat kann sich mit jeder Konzernreorganisation verschieben. Vor jedem Erstkontakt einzeln nachrecherchieren.

Sheet Ausgeschlossen
A1: Grund | B1: Unternehmen
A2: Pharma & Life Sciences | B2: Roche, Novartis, Lonza, Bachem, Siegfried, PolyPeptide — Wirkstoffentwicklung und CDMO, kein Engineered Product.
A3: Lebensmittel & Ingredients | B3: Nestlé, Barry Callebaut, Givaudan, dsm-firmenich, Emmi, Lindt — Nahrungsmittel bzw. Aroma- und Nährstoffchemie.
A4: Dienstleistungen, Handel, Software | B4: Adecco, Kühne+Nagel, ALSO Holding, Implenia, Burkhalter, Kudelski, Dufry — kein eigenes technisches Produkt. SGS ist als Grenzfall in der Hauptliste geführt.
A5: Rohstoffhandel | B5: Glencore, Trafigura, Bunge — Handel und Verarbeitung, keine Industriegüter.
A6: Sitz Liechtenstein, nicht Schweiz | B6: Hilti (Schaan), Ivoclar (Schaan), thyssenkrupp Presta (Eschen), Hoval (Vaduz).
A7: Sitz im Ausland trotz Schweizer Ruf | B7: TE Connectivity (Irland), Precipart (USA), Mubea (DE), Almatec (DE), Autoliv (SE). ams-OSRAM (Österreich) und STMicroelectronics (Amsterdam) sind als Grenzfälle in der Hauptliste.
A8: Unter CHF 100 Mio. Umsatz | B8: Contrinex (~CHF 60–65 Mio.), Datacolor (~CHF 86 Mio.), Agathon, Wandfluh, Regloplas, Sylvac, Bachofen, Gerber Instruments, Jansen (Zahl unbestätigt).
A9: Status unklar oder entfallen | B9: Meyer Burger (Insolvenz von Tochtergesellschaften), Saurer (Konzernmutter chinesisch), Schleuniger (in Komax aufgegangen).
A10: Geprüft, aber nur Landesgesellschaft | B10: Bosch (Zuchwil), Bosch Rexroth, Schaeffler, ZF, Mahle, WAGO, Festo, Rockwell, Atlas Copco, SKF, Kongsberg, Vestas, Nordex, Thales, Leonardo, BAE, Collins Aerospace, Nidec (Birmenstorf), Demant, WSAudiology, Siemens Healthineers, Philips, GE HealthCare, Agilent, Waters, Sartorius, Revvity, ASML, Lam Research, Applied Materials — kein internationales Mandat am Schweizer Standort belegbar.
A11: Sonderfälle | B11: TE Connectivity: Sitz 2024 nach Irland verlegt, verbleibendes Regionalmandat in Schaffhausen nicht belegbar. Alcon und SHL Medical: Schweizer Gesellschaften, kein ausländischer Mutterkonzern — Alcon steht bereits in der Hauptliste. Roche Diagnostics Rotkreuz: Mutterkonzern schweizerisch. TDK-Micronas: Sitz Freiburg im Breisgau, nicht Fribourg.
